Workbook

Sheet Summary
A1: SmartCiti.X ~ Holodeck — investor data pack
A2: Every figure below is a formula over the data sheets, which the repository's own generator (tools/gen_investor.mjs) writes from the catalog, the eval report and the world data. No revenue, price, market or user figure appears anywhere.
A3: Measure | B3: Value | C3: Where it comes from
A4: Content
A5: Graded procedures | B5: =COUNTA(Stations!$A$2:$A$634) -> 633 | C5: Stations sheet, one row per procedure
A6: Training programmes | B6: =COUNTA(Programmes!$A$2:$A$55) -> 54 | C6: Programmes sheet
A7: Stations counted across programmes | B7: =SUM(Programmes!$D$2:$D$55) -> 683 | C7: a station can sit in more than one programme
A8: Mean content eval score | B8: =ROUND(AVERAGE(Stations!$K$2:$K$634),1) -> 95.8 | C8: tools/eval_content.mjs, 0–100
A9: Procedures scoring 95 or more | B9: =COUNTIF(Stations!$K$2:$K$634,">=95") -> 513
A10: Procedures scoring 90 to 94 | B10: =COUNTIFS(Stations!$K$2:$K$634,">=90",Stations!$K$2:$K$634,"<95") -> 115
A11: Procedures under 90 | B11: =COUNTIF(Stations!$K$2:$K$634,"<90") -> 5 | C11: flat sourced briefings and readings
A12: Share at 90 or more | B12: =IFERROR(COUNTIF(Stations!$K$2:$K$634,">=90")/COUNTA(Stations!$A$2:$A$634),0) -> 0.99210111
A13: Total interaction steps | B13: =SUM(Stations!$F$2:$F$634) -> 8473
A14: Total hazards to find | B14: =SUM(Stations!$H$2:$H$634) -> 2550
A15: Unions in the registry | B15: =COUNTA(Unions!$A$2:$A$112) -> 111 | C15: Unions sheet
A16: Checkers passing on every change | B16: =IFERROR(INDEX('Platform Facts'!$B$2:$B$50,MATCH("checkers",'Platform Facts'!$A$2:$A$50,0)),"-") -> 61 | C16: tools/check_all.mjs
A17: Worlds and assets
A18: Open worlds and scenic districts | B18: =COUNTA(Worlds!$A$2:$A$12) -> 11 | C18: Worlds sheet
A19: Job sites across the worlds | B19: =SUM(Worlds!$E$2:$E$12) -> 82
A20: Quests across the worlds | B20: =SUM(Worlds!$I$2:$I$12) -> 153
A21: Easter eggs across the worlds | B21: =SUM(Worlds!$J$2:$J$12) -> 58
A22: Scored activities across the worlds | B22: =SUM(Worlds!$K$2:$K$12) -> 15
A23: 3D builders (equipment, vehicles, boats, props, tools, wildlife) | B23: =COUNTA(Assets!$A$2:$A$132) -> 131 | C23: Assets sheet
A24: Vehicles | B24: =COUNTIF('Vehicles and Boats'!$B$2:$B$33,"vehicle") -> 20 | C24: Vehicles and Boats sheet
A25: Boats and underwater vehicles | B25: =COUNTIF('Vehicles and Boats'!$B$2:$B$33,"boat") -> 12
A26: Builders exported to Unity | B26: =COUNTIF(Assets!$J$2:$J$132,"yes") -> 90 | C26: exports/unity/SmartCitiX/Models/MANIFEST.json
A27: Interfaces
A28: App pages and interfaces | B28: =COUNTA('UI Surfaces'!$A$2:$A$67) -> 66 | C28: UI Surfaces sheet
A30: Largest programmes by station count
A31: Programme | B31: Stations | C31: Eval mean
A32: =INDEX(Programmes!$B$2:$B$55,MATCH(LARGE(Programmes!$M$2:$M$55,1),Programmes!$M$2:$M$55,0)) -> Bay Area Union Edition — Sheet Metal, Bridge, Port and Marine | B32: =INDEX(Programmes!$D$2:$D$55,MATCH(LARGE(Programmes!$M$2:$M$55,1),Programmes!$M$2:$M$55,0)) -> 42 | C32: =INDEX(Programmes!$L$2:$L$55,MATCH(LARGE(Programmes!$M$2:$M$55,1),Programmes!$M$2:$M$55,0)) -> 96.5
A33: =INDEX(Programmes!$B$2:$B$55,MATCH(LARGE(Programmes!$M$2:$M$55,2),Programmes!$M$2:$M$55,0)) -> Pathway Edition — wojrc.org | B33: =INDEX(Programmes!$D$2:$D$55,MATCH(LARGE(Programmes!$M$2:$M$55,2),Programmes!$M$2:$M$55,0)) -> 40 | C33: =INDEX(Programmes!$L$2:$L$55,MATCH(LARGE(Programmes!$M$2:$M$55,2),Programmes!$M$2:$M$55,0)) -> 95.7
A34: =INDEX(Programmes!$B$2:$B$55,MATCH(LARGE(Programmes!$M$2:$M$55,3),Programmes!$M$2:$M$55,0)) -> SF Bay Restoration & Cleanup — Maritime and Underwater | B34: =INDEX(Programmes!$D$2:$D$55,MATCH(LARGE(Programmes!$M$2:$M$55,3),Programmes!$M$2:$M$55,0)) -> 35 | C34: =INDEX(Programmes!$L$2:$L$55,MATCH(LARGE(Programmes!$M$2:$M$55,3),Programmes!$M$2:$M$55,0)) -> 96.3
A35: =INDEX(Programmes!$B$2:$B$55,MATCH(LARGE(Programmes!$M$2:$M$55,4),Programmes!$M$2:$M$55,0)) -> Job Readiness Edition — wojrc.org programmes | B35: =INDEX(Programmes!$D$2:$D$55,MATCH(LARGE(Programmes!$M$2:$M$55,4),Programmes!$M$2:$M$55,0)) -> 32 | C35: =INDEX(Programmes!$L$2:$L$55,MATCH(LARGE(Programmes!$M$2:$M$55,4),Programmes!$M$2:$M$55,0)) -> 95.7
A36: =INDEX(Programmes!$B$2:$B$55,MATCH(LARGE(Programmes!$M$2:$M$55,5),Programmes!$M$2:$M$55,0)) -> Hunters Point Edition — Can We Live? | B36: =INDEX(Programmes!$D$2:$D$55,MATCH(LARGE(Programmes!$M$2:$M$55,5),Programmes!$M$2:$M$55,0)) -> 26 | C36: =INDEX(Programmes!$L$2:$L$55,MATCH(LARGE(Programmes!$M$2:$M$55,5),Programmes!$M$2:$M$55,0)) -> 94
A37: =INDEX(Programmes!$B$2:$B$55,MATCH(LARGE(Programmes!$M$2:$M$55,6),Programmes!$M$2:$M$55,0)) -> Hunters Point Clean-up and Bay Restoration | B37: =INDEX(Programmes!$D$2:$D$55,MATCH(LARGE(Programmes!$M$2:$M$55,6),Programmes!$M$2:$M$55,0)) -> 26 | C37: =INDEX(Programmes!$L$2:$L$55,MATCH(LARGE(Programmes!$M$2:$M$55,6),Programmes!$M$2:$M$55,0)) -> 94.5
A38: =INDEX(Programmes!$B$2:$B$55,MATCH(LARGE(Programmes!$M$2:$M$55,7),Programmes!$M$2:$M$55,0)) -> Situational Awareness — Interruption Drill | B38: =INDEX(Programmes!$D$2:$D$55,MATCH(LARGE(Programmes!$M$2:$M$55,7),Programmes!$M$2:$M$55,0)) -> 22 | C38: =INDEX(Programmes!$L$2:$L$55,MATCH(LARGE(Programmes!$M$2:$M$55,7),Programmes!$M$2:$M$55,0)) -> 94.8
A39: =INDEX(Programmes!$B$2:$B$55,MATCH(LARGE(Programmes!$M$2:$M$55,8),Programmes!$M$2:$M$55,0)) -> Property Management — Twenty Zones | B39: =INDEX(Programmes!$D$2:$D$55,MATCH(LARGE(Programmes!$M$2:$M$55,8),Programmes!$M$2:$M$55,0)) -> 21 | C39: =INDEX(Programmes!$L$2:$L$55,MATCH(LARGE(Programmes!$M$2:$M$55,8),Programmes!$M$2:$M$55,0)) -> 97.6
A40: =INDEX(Programmes!$B$2:$B$55,MATCH(LARGE(Programmes!$M$2:$M$55,9),Programmes!$M$2:$M$55,0)) -> Dental Careers — Unspoken Smiles | B40: =INDEX(Programmes!$D$2:$D$55,MATCH(LARGE(Programmes!$M$2:$M$55,9),Programmes!$M$2:$M$55,0)) -> 19 | C40: =INDEX(Programmes!$L$2:$L$55,MATCH(LARGE(Programmes!$M$2:$M$55,9),Programmes!$M$2:$M$55,0)) -> 96.7
A41: =INDEX(Programmes!$B$2:$B$55,MATCH(LARGE(Programmes!$M$2:$M$55,10),Programmes!$M$2:$M$55,0)) -> Dental Hygiene — Unspoken Smiles | B41: =INDEX(Programmes!$D$2:$D$55,MATCH(LARGE(Programmes!$M$2:$M$55,10),Programmes!$M$2:$M$55,0)) -> 19 | C41: =INDEX(Programmes!$L$2:$L$55,MATCH(LARGE(Programmes!$M$2:$M$55,10),Programmes!$M$2:$M$55,0)) -> 97.1

Sheet Pilot Planner
A1: Pilot planner — a template for a partner cohort
A2: Blue cells on a yellow ground are inputs: change them. Row 5 holds example values only, to show the format; replace them with the pilot's real plan. Black cells are formulas.
A4: Input | B4: Value | C4: Note
A5: Programme id (from the Programmes sheet) | B5: wojrc-pathway-edition | C5: Example value — replace
A6: Learners in the cohort | B6: 12 | C6: Example value — replace
A7: Weeks in the pilot | B7: 8 | C7: Example value — replace
A8: Practice sessions per learner per week | B8: 2 | C8: Example value — replace
A9: Stations attempted per session | B9: 3 | C9: Example value — replace
A11: Derived | B11: Value
A12: Programme name | B12: =IFERROR(INDEX(Programmes!$B$2:$B$55,MATCH($B$5,Programmes!$A$2:$A$55,0)),"id not found") -> Pathway Edition — wojrc.org
A13: Stations in the programme | B13: =IFERROR(INDEX(Programmes!$D$2:$D$55,MATCH($B$5,Programmes!$A$2:$A$55,0)),0) -> 40
A14: Eval mean of its stations | B14: =IFERROR(INDEX(Programmes!$L$2:$L$55,MATCH($B$5,Programmes!$A$2:$A$55,0)),0) -> 95.7
A15: Station attempts across the cohort | B15: =B6*B7*B8*B9 -> 576
A16: Attempts per learner | B16: =B7*B8*B9 -> 48
A17: Times each learner could run every station | B17: =IFERROR(B16/B13,0) -> 1.2

Sheet Programmes
A1: id | B1: name | C1: categoryMix | D1: stationCount | E1: unions | F1: trainingBodies | G1: competencyRequire | H1: ladderLevels | I1: ladderLevelsFull | J1: bayWorldSites | K1: deepSites | L1: evalMean | M1: rankKey
A2: electrical-first-period | B2: Inside Wireman — First Period | C2: Energy & Power: 7; Trade Skills Simulator: 1 | D2: 8 | E2: ibew | F2: ibew-neca-jatc | G2: 4 | H2: 20 | I2: 19 | J2: west-oakland-substation-yard | L2: 96.6 | M2: =D2+ROW()/100000 -> 8.00002
A3: confined-space | B3: Confined Space — Entry and Rescue | C3: Water & Environmental: 7; Emergency Services: 1 | D3: 8 | E3: iaff; iuoe; liuna; ua | F3: iaff-training; iuoe-training; liuna-training-fund; ua-apprenticeship | G3: 4 | H3: 20 | I3: 20 | J3: south-treatment-plant; west-oakland-utility-yard | K3: outfall-intake-lockout-site | L3: 96.3 | M3: =D3+ROW()/100000 -> 8.00003
A4: fall-protection | B4: Working at Height — Fall Protection | C4: Construction & Structural Trades: 4; Connectivity & Telecom: 2; Emergency Services: 1 | D4: 7 | E4: carpenters; cwa; ironworkers | F4: carpenters-ictf; cwa-training; ironworkers-impact | G4: 4 | H4: 20 | I4: 20 | J4: downtown-tower-site | L4: 95.6 | M4: =D4+ROW()/100000 -> 7.00004
A5: hazmat-environmental | B5: Hazmat and Environmental Response | C5: Environmental Monitoring: 6; Emergency Services: 2; Surface Prep & Coatings: 1; Water & Environmental: 1 | D5: 10 | E5: iaff; liuna | F5: iaff-training; liuna-training-fund | G5: 5 | H5: 20 | I5: 20 | J5: port-hazmat-response-yard | K5: outfall-diffuser-inspection | L5: 92.5 | M5: =D5+ROW()/100000 -> 10.00005
A6: rigging-lifting | B6: Rigging and Lifting | C6: Entertainment & Live Events: 3; Construction & Structural Trades: 2; Maritime & Ports: 1 | D6: 6 | E6: iatse; ilwu; ironworkers; iuoe | F6: iatse-training-trust; ilwu-pma-training; ironworkers-impact; iuoe-training | G6: 3 | H6: 20 | I6: 20 | J6: port-container-terminal | K6: shelf-lift-bag-site; wreck-salvage-rigging | L6: 93.8 | M6: =D6+ROW()/100000 -> 6.00006
A7: stationary-engineer | B7: Stationary Engineer — Building Plant | C7: Building Systems & Facilities: 7 | D7: 7 | E7: iuoe | F7: iuoe-training; ua-apprenticeship | G7: 4 | H7: 20 | I7: 20 | J7: downtown-central-plant; south-treatment-plant | L7: 93.3 | M7: =D7+ROW()/100000 -> 7.00007
A8: port-operations | B8: Port and Terminal Operations | C8: Maritime & Ports: 7 | D8: 7 | E8: ilwu; meba; siu; teamsters | F8: ilwu-pma-training; meba-calhoon-school; siu-paul-hall-center; teamsters-training | G8: 4 | H8: 20 | I8: 20 | J8: channel-buoy-tender-pier; island-yacht-harbor; port-container-terminal; south-shoreline-marina | K8: approach-buoy-tender-station; reef-ball-placement-site | L8: 94.3 | M8: =D8+ROW()/100000 -> 7.00008
A9: transit-ramp | B9: Transit and Ramp Operations | C9: Mobility & Transit: 6; Manufacturing & Automation: 1 | D9: 7 | E9: atu; iam; ibew; twu | F9: atu-training; bmwed-training; iam-winpisinger-center; ibew-neca-jatc; twu-training | G9: 4 | H9: 20 | I9: 20 | J9: coliseum-elevated-transit-station; island-ferry-landing | L9: 94.7 | M9: =D9+ROW()/100000 -> 7.00009
A10: energy-transition | B10: Energy Transition Systems | C10: Energy & Power: 8; Connectivity & Telecom: 1 | D10: 9 | E10: ibew | F10: ibew-neca-jatc | G10: 5 | H10: 20 | I10: 20 | J10: hills-transmission-corridor; ridge-reservoir-yard | L10: 97.1 | M10: =D10+ROW()/100000 -> 9.0001
A11: live-events | B11: Live Events Production | C11: Entertainment & Live Events: 7 | D11: 7 | E11: iatse | F11: iatse-training-trust | G11: 4 | H11: 20 | I11: 20 | J11: coliseum-stadium | L11: 95.3 | M11: =D11+ROW()/100000 -> 7.00011
A12: hunters-point-bay-restoration | B12: Hunters Point Clean-up and Bay Restoration | C12: Environmental Monitoring: 11; Water & Environmental: 9; Maritime & Ports: 3; Building Systems & Facilities: 1; Emergency Services: 1; Energy & Power: 1 | D12: 26 | E12: carpenters; ibu; iuoe; iuoe-local3; liuna; teamsters; ua | F12: carpenters-ictf; ilwu-pma-training; iuoe-local3-training; iuoe-training; liuna-training-fund; teamsters-training; ua-apprenticeship | G12: 6 | H12: 20 | I12: 20 | J12: estuary-shoreline-park-trailhead; north-shoreline-field-lab | K12: channel-dredge-survey; eelgrass-transplant-plots; marsh-mouth-invasive-plot; marsh-mouth-tide-gate; mud-plain-hotspot-survey; pier-creosote-pile-site; reef-ball-monitoring-plot | L12: 94.5 | M12: =D12+ROW()/100000 -> 26.00012
A13: culinary-kitchen | B13: Culinary — The Working Kitchen | C13: Culinary & Hospitality: 15; Trade Skills Simulator: 1 | D13: 16 | E13: afscme; seiu; unite-here | F13: afscme-training; seiu-training; unite-here-training | G13: 6 | H13: 20 | I13: 20 | J13: uptown-restaurant-row | L13: 94.1 | M13: =D13+ROW()/100000 -> 16.00013
A14: dental-hygiene-unspoken-smiles | B14: Dental Hygiene — Unspoken Smiles | C14: Dental & Oral Health: 18; Trade Skills Simulator: 1 | D14: 19 | E14: afscme; seiu; ufcw | F14: afscme-training; seiu-training; ufcw-training | G14: 6 | H14: 20 | I14: 20 | J14: fruitvale-community-college | L14: 97.1 | M14: =D14+ROW()/100000 -> 19.00014
A15: dental-careers-unspoken-smiles | B15: Dental Careers — Unspoken Smiles | C15: Dental & Oral Health: 19 | D15: 19 | E15: afscme; seiu; ufcw | F15: afscme-training; seiu-training; ufcw-training | G15: 6 | H15: 20 | I15: 20 | J15: fruitvale-community-college | L15: 96.7 | M15: =D15+ROW()/100000 -> 19.00015
A16: civic-leadership-and-ei | B16: Civic Leadership and Emotional Intelligence | C16: Community Environmental Justice: 17 | D16: 17 | E16: afscme; seiu | F16: afscme-training; seiu-training | G16: 6 | H16: 20 | I16: 20 | J16: downtown-civic-center | L16: 96.4 | M16: =D16+ROW()/100000 -> 17.00016
A17: property-management | B17: Property Management — Twenty Zones | C17: Building Systems & Facilities: 21 | D17: 21 | E17: iuoe; seiu; seiu-uswtw; unite-here | F17: iuoe-training; seiu-training; seiu-uswtw-training; unite-here-training | G17: 6 | H17: 20 | I17: 20 | J17: downtown-housing-block | L17: 97.6 | M17: =D17+ROW()/100000 -> 21.00017
A18: outbreak-response-who | B18: Outbreak and Disease Response — WHO and UN Practice | C18: Emergency Services: 11 | D18: 11 | E18: afscme; cna; nnu; seiu | F18: afscme-training; seiu-training | G18: 6 | H18: 20 | I18: 20 | J18: coliseum-area-hospital; emery-lab-campus | L18: 97.6 | M18: =D18+ROW()/100000 -> 11.00018
A19: job-readiness-edition | B19: Job Readiness Edition — wojrc.org programmes | C19: Mobility & Transit: 16; Community Environmental Justice: 15; Manufacturing & Automation: 1 | D19: 32 | E19: afscme; ilwu; seiu; teamsters | F19: afscme-training; ilwu-pma-training; seiu-training; teamsters-training | G19: 6 | H19: 20 | I19: 20 | J19: emery-distribution-center; west-oakland-truck-yard | L19: 95.7 | M19: =D19+ROW()/100000 -> 32.00019
A20: bay-area-union-edition | B20: Bay Area Union Edition — Sheet Metal, Bridge, Port and Marine | C20: Maritime & Ports: 24; Construction & Structural Trades: 9; Manufacturing & Automation: 9 | D20: 42 | E20: carpenters; ibu; ilwu; ironworkers; iuoe; iupat; meba; siu; smart | F20: carpenters-ictf; ilwu-pma-training; ironworkers-impact; iuoe-training; iupat-fti; meba-calhoon-school; siu-paul-hall-center; smart-iti | G20: 6 | H20: 20 | I20: 20 | J20: island-boatyard; island-ferry-landing; island-yacht-harbor; west-oakland-union-hall | K20: approach-boom-tow-site; channel-scour-survey; flats-workboat-anchorage; kelp-night-line-site; outfall-intake-lockout-site; pier-piling-inspection-station; shelf-lift-bag-site; trench-rov-station; wreck-photo-survey | L20: 96.5 | M20: =D20+ROW()/100000 -> 42.0002
A21: bartending-course | B21: Bartending — Behind the Bar | C21: Culinary & Hospitality: 15; Trade Skills Simulator: 1 | D21: 16 | E21: unite-here | F21: unite-here-training | G21: 6 | H21: 20 | I21: 20 | J21: uptown-theatre-district | L21: 94.6 | M21: =D21+ROW()/100000 -> 16.00021
A22: hunters-point-can-we-live | B22: Hunters Point Edition — Can We Live? | C22: Community Environmental Justice: 26 | D22: 26 | E22: iuoe; liuna; teamsters | F22: iuoe-training; liuna-training-fund; seiu-training; teamsters-training | G22: 6 | H22: 20 | I22: 20 | J22: estuary-shoreline-park-trailhead | K22: flats-sediment-core-site; outfall-discharge-photo-point | L22: 94 | M22: =D22+ROW()/100000 -> 26.00022
A23: sewing-garment-trades | B23: Sewing and Garment Trades | C23: Sewing & Garment Trades: 10; Trade Skills Simulator: 1 | D23: 11 | E23: seiu; unite-here; workers-united | F23: seiu-training; unite-here-training | G23: 6 | H23: 20 | I23: 20 | J23: west-oakland-warehouse-district | L23: 96.2 | M23: =D23+ROW()/100000 -> 11.00023
A24: bridge-and-structural | B24: Bridge and Structural Trades | C24: Construction & Structural Trades: 7 | D24: 7 | E24: ironworkers; iuoe; iupat; liuna | F24: ironworkers-impact; iuoe-training; iupat-fti; liuna-training-fund | G24: 4 | H24: 20 | I24: 20 | J24: bridge-approach-toll-plaza | K24: channel-scour-survey | L24: 95.6 | M24: =D24+ROW()/100000 -> 7.00024
A25: hotel-workers | B25: Hotel Workers — Back of House | C25: Culinary & Hospitality: 7 | D25: 7 | E25: unite-here | F25: unite-here-training | G25: 4 | H25: 20 | I25: 20 | J25: uptown-hotel-row | L25: 96.9 | M25: =D25+ROW()/100000 -> 7.00025
A26: builders-trades | B26: Builders — Carpenters, Laborers and Masons | C26: Construction & Structural Trades: 8 | D26: 8 | E26: bac; carpenters; iuoe; liuna | F26: bac-imi; carpenters-ictf; iuoe-training; liuna-training-fund | G26: 4 | H26: 20 | I26: 20 | J26: uptown-construction-site | L26: 96.1 | M26: =D26+ROW()/100000 -> 8.00026
A27: first-responders | B27: First Responders — Fire, EMS, Police, Crisis and Relief | C27: Emergency Services: 17 | D27: 17 | E27: afscme; fop; iaff; liuna; nage; nasw; seiu; seiu-1021 | F27: afscme-training; iaff-training; liuna-training-fund; naemt-courses; nasw-code-of-ethics; seiu-1021-training; seiu-training | G27: 6 | H27: 20 | I27: 20 | J27: fruitvale-fire-station; ridge-fire-lookout | K27: seamount-capstone-survey | L27: 95.8 | M27: =D27+ROW()/100000 -> 17.00027
A28: situational-awareness | B28: Situational Awareness — Interruption Drill | C28: Building Systems & Facilities: 3; Construction & Structural Trades: 3; Energy & Power: 3; Trade Skills Simulator: 3; Connectivity & Telecom: 2; Emergency Services: 2; Manufacturing & Automation: 2; Water & Environmental: 2; Maritime & Ports: 1; Mobility & Transit: 1 | D28: 22 | E28: iaff; ibew; ironworkers; liuna; ua | F28: iaff-training; ibew-neca-jatc; ironworkers-impact; liuna-training-fund; ua-apprenticeship | G28: 6 | H28: 20 | I28: 20 | J28: lake-loop-boathouse | K28: shelf-checkout-site | L28: 94.8 | M28: =D28+ROW()/100000 -> 22.00028
A29: ports-maritime-ecology | B29: Ports, Maritime and Bay Ecology | C29: Maritime & Ports: 11 | D29: 11 | E29: ibew; ibu; ilwu; liuna | F29: afscme-training; ibew-neca-jatc; ilwu-pma-training; liuna-training-fund | G29: 6 | H29: 20 | I29: 20 | J29: channel-buoy-tender-pier; estuary-research-dock; north-marina-pier | K29: approach-buoy-tender-station; reef-ball-monitoring-plot | L29: 94.3 | M29: =D29+ROW()/100000 -> 11.00029
A30: air-quality-monitoring | B30: Air Quality — Monitoring and Control | C30: Environmental Monitoring: 6 | D30: 6 | E30: afscme; iuoe; liuna; usw | F30: afscme-training; iuoe-training; liuna-training-fund; usw-mazzocchi-center | G30: 3 | H30: 20 | I30: 20 | J30: north-shoreline-field-lab; west-oakland-air-monitoring-post | K30: flats-sonde-station | L30: 94.2 | M30: =D30+ROW()/100000 -> 6.0003
A31: basketball-fundamentals | B31: Basketball Fundamentals | C31: Youth Sports & Coaching: 18 | D31: 18 | E31: afscme; seiu | F31: afscme-training; seiu-training | G31: 6 | H31: 20 | I31: 20 | J31: coliseum-arena | L31: 96.5 | M31: =D31+ROW()/100000 -> 18.00031
A32: bay-restoration-maritime-underwater | B32: SF Bay Restoration & Cleanup — Maritime and Underwater | C32: Maritime & Ports: 16; Environmental Monitoring: 10; Water & Environmental: 9 | D32: 35 | E32: afscme; carpenters; ibu; ilwu; iuoe; iuoe-local3; liuna; meba; seiu; siu | F32: afscme-training; carpenters-ictf; ilwu-pma-training; iuoe-local3-training; iuoe-training; liuna-training-fund; meba-calhoon-school; seiu-training; siu-paul-hall-center | G32: 6 | H32: 20 | I32: 20 | J32: estuary-marina-boatyard; island-boatyard; north-marina-pier; north-shoreline-field-lab; south-shoreline-marina | K32: approach-boom-tow-site; channel-dredge-survey; eelgrass-fish-census-line; eelgrass-turbidity-curtain; flats-sediment-core-site; flats-sonde-station; flats-workboat-anchorage; kelp-transect-start; marsh-mouth-culvert; marsh-mouth-invasive-plot; mud-plain-hotspot-survey; mud-plain-trash-capture; pier-surface-supplied-station; reef-ball-placement-site; seamount-capstone-survey; shelf-checkout-site; shelf-debris-sweep; wreck-photo-survey; wreck-salvage-rigging | L32: 96.3 | M32: =D32+ROW()/100000 -> 35.00032
A33: railroad-crafts | B33: Railroad Crafts — Track, Car and Cab | C33: Mobility & Transit: 8 | D33: 8 | E33: blet; bmwed; smart; smart-td | F33: blet-training; bmwed-training; smart-iti; smarttd-training | G33: 4 | H33: 20 | I33: 20 | J33: port-rail-yard | L33: 95.3 | M33: =D33+ROW()/100000 -> 8.00033
A34: heavy-equipment-operators | B34: Heavy Equipment Operators — IUOE Local 3 | C34: Construction & Structural Trades: 8 | D34: 8 | E34: iuoe | F34: iuoe-training | G34: 4 | H34: 20 | I34: 20 | J34: hills-grading-site; ridge-reservoir-yard | K34: pier-creosote-pile-site | L34: 94.9 | M34: =D34+ROW()/100000 -> 8.00034
A35: plumbers-and-pipefitters | B35: Plumbers and Pipefitters — Journeyman Rough-In and Test Block | C35: Building Systems & Facilities: 7; Water & Environmental: 1 | D35: 8 | E35: ua | F35: ua-apprenticeship | G35: 4 | H35: 20 | I35: 20 | J35: port-maintenance-shop | L35: 96.5 | M35: =D35+ROW()/100000 -> 8.00035
A36: glaziers-and-architectural-metal | B36: Glaziers and Architectural Metal | C36: Construction & Structural Trades: 8 | D36: 8 | E36: iupat; iupat-dc16 | F36: iupat-dc16-glaziers; iupat-fti | G36: 4 | H36: 20 | I36: 20 | J36: downtown-tower-site | L36: 95.6 | M36: =D36+ROW()/100000 -> 8.00036
A37: elevator-constructors | B37: Elevator Constructor — IUEC Core Skills | C37: Building Systems & Facilities: 8 | D37: 8 | E37: iuec | F37: neiep-training | G37: 4 | H37: 20 | I37: 20 | J37: downtown-tower-site | L37: 95.1 | M37: =D37+ROW()/100000 -> 8.00037
A38: insulators-and-boilermakers | B38: Insulators and Boilermakers — Building Systems | C38: Building Systems & Facilities: 8 | D38: 8 | E38: ibb; insulators | F38: boilermakers-local-549; insulators-local-16 | G38: 4 | H38: 20 | I38: 20 | J38: port-maintenance-shop | L38: 96.6 | M38: =D38+ROW()/100000 -> 8.00038
A39: cement-masons-and-plasterers | B39: Cement Masons and Plasterers | C39: Construction & Structural Trades: 8 | D39: 8 | E39: opcmia | F39: opcmia-local-300 | G39: 4 | H39: 20 | I39: 20 | J39: uptown-construction-site | L39: 96.1 | M39: =D39+ROW()/100000 -> 8.00039
A40: healthcare-support | B40: Healthcare Support | C40: Healthcare Support: 8 | D40: 8 | E40: nuhw; seiu; seiu-uhw | F40: nuhw-training; seiu-training; seiu-uhw-training | G40: 4 | H40: 20 | I40: 20 | J40: coliseum-area-hospital; emery-lab-campus | L40: 96 | M40: =D40+ROW()/100000 -> 8.0004
A41: roofers-and-waterproofers | B41: Roofers and Waterproofers | C41: Construction & Structural Trades: 8 | D41: 8 | E41: urw | F41: roofers-local-40-training | G41: 4 | H41: 20 | I41: 20 | J41: downtown-housing-block | L41: 96 | M41: =D41+ROW()/100000 -> 8.00041
A42: water-and-gas-utility-crews | B42: Water and Gas Utility Crews — Distribution Authority | C42: Energy & Power: 4; Water & Environmental: 4 | D42: 8 | E42: ibew; uwua | F42: ibew-neca-jatc; uwua-training | G42: 4 | H42: 20 | I42: 20 | J42: ridge-reservoir-yard; south-treatment-plant; west-oakland-utility-yard | K42: outfall-diffuser-inspection | L42: 97 | M42: =D42+ROW()/100000 -> 8.00042
A43: aviation-maintenance-and-ground | B43: Aviation Maintenance and Ground — IAM/TWU Ramp and Line | C43: Mobility & Transit: 8 | D43: 8 | E43: iam; twu | F43: iam-winpisinger-center; twu-training | G43: 4 | H43: 20 | I43: 20 | J43: coliseum-airfield-apron; island-airfield-park | L43: 95.4 | M43: =D43+ROW()/100000 -> 8.00043
A44: warehouse-and-logistics-automation | B44: Warehouse and Logistics Automation — Teamsters Distribution Floor | C44: Manufacturing & Automation: 8 | D44: 8 | E44: teamsters | F44: teamsters-training | G44: 4 | H44: 20 | I44: 20 | J44: emery-distribution-center; west-oakland-warehouse-district | L44: 95.6 | M44: =D44+ROW()/100000 -> 8.00044
A45: education-support-staff | B45: Education Support Staff — Custodial, Grounds, Transport and Classroom | C45: Building Systems & Facilities: 5; Mobility & Transit: 2; Culinary & Hospitality: 1 | D45: 8 | E45: aft; csea | F45: aft-training; csea-training | G45: 4 | H45: 20 | I45: 20 | J45: fruitvale-elementary-school | L45: 96.6 | M45: =D45+ROW()/100000 -> 8.00045
A46: grounds-and-landscaping | B46: Grounds & Landscaping Crew | C46: Grounds & Landscaping: 12 | D46: 12 | E46: afscme; liuna; seiu | F46: afscme-training; liuna-training-fund; seiu-training | G46: 6 | H46: 20 | I46: 20 | J46: hills-redwood-park-grounds-shop; island-airfield-park | L46: 94.3 | M46: =D46+ROW()/100000 -> 12.00046
A47: wojrc-pathway-edition | B47: Pathway Edition — wojrc.org | C47: Community Environmental Justice: 21; Mobility & Transit: 18; Manufacturing & Automation: 1 | D47: 40 | E47: afscme; seiu; teamsters | F47: afscme-training; ilwu-pma-training; seiu-training; teamsters-training | G47: 6 | H47: 20 | I47: 20 | J47: port-container-terminal | L47: 95.7 | M47: =D47+ROW()/100000 -> 40.00047
A48: grocery-and-meatpacking | B48: Grocery and Meatpacking — UFCW Store and Plant Floor | C48: Culinary & Hospitality: 8 | D48: 8 | E48: ufcw | F48: ufcw-training | G48: 4 | H48: 20 | I48: 20 | J48: uptown-restaurant-row | L48: 93.1 | M48: =D48+ROW()/100000 -> 8.00048
A49: airline-cabin-and-flight-crew | B49: Airline Cabin and Flight Crew — AFA-CWA and ALPA | C49: Mobility & Transit: 8 | D49: 8 | E49: afa-cwa; alpa; cwa | F49: afa-cwa-training; alpa-training; cwa-training | G49: 4 | H49: 20 | I49: 20 | J49: west-oakland-truck-yard | L49: 94.9 | M49: =D49+ROW()/100000 -> 8.00049
A50: mill-and-mine | B50: Mill and Mine | C50: Manufacturing & Automation: 8 | D50: 8 | E50: umwa; usw | F50: umwa-training; usw-mazzocchi-center | G50: 4 | H50: 20 | I50: 20 | J50: port-maintenance-shop | L50: 95.1 | M50: =D50+ROW()/100000 -> 8.0005
A51: screen-and-media-crafts | B51: Screen & Media Crafts | C51: Entertainment & Live Events: 8 | D51: 8 | E51: aea; afm; cwa; iatse; newsguild-cwa; sag-aftra | F51: aea-training; afm-training; cwa-training; iatse-training-trust; newsguild-cwa-training; sag-aftra-training | G51: 4 | H51: 20 | I51: 20 | J51: uptown-theatre-district | L51: 96.8 | M51: =D51+ROW()/100000 -> 8.00051
A52: postal-and-mail-processing | B52: Postal & Mail Processing Crew | C52: Manufacturing & Automation: 4; Mobility & Transit: 4 | D52: 8 | E52: apwu; nalc; npmhu | F52: apwu-training; nalc-training; npmhu-training | G52: 4 | H52: 20 | I52: 20 | J52: west-oakland-truck-yard | L52: 96.1 | M52: =D52+ROW()/100000 -> 8.00052
A53: yacht-and-charter-crew | B53: Yacht & Charter Crew | C53: Maritime & Ports: 8 | D53: 8 | E53: ibu; meba; siu | F53: ilwu-pma-training; meba-calhoon-school; siu-paul-hall-center | G53: 4 | H53: 20 | I53: 20 | J53: estuary-marina-boatyard; island-yacht-harbor | L53: 95.8 | M53: =D53+ROW()/100000 -> 8.00053
A54: marine-ecology-and-restoration | B54: Marine Ecology & Restoration — Survey and Restoration Crews | C54: Water & Environmental: 8 | D54: 8 | E54: afscme; cwa; liuna; seiu; seiu-1021; upte-cwa | F54: afscme-training; cwa-training; liuna-training-fund; seiu-1021-training; seiu-training; upte-cwa-training | G54: 4 | H54: 20 | I54: 20 | J54: channel-buoy-tender-pier; estuary-research-dock; north-shoreline-field-lab | K54: eelgrass-fish-census-line; eelgrass-transplant-plots; flats-sediment-core-site; kelp-transect-start; marsh-mouth-tide-gate; reef-ball-monitoring-plot; seamount-capstone-survey | L54: 97.3 | M54: =D54+ROW()/100000 -> 8.00054
A55: commercial-diving-and-scientific-scuba | B55: Commercial Diving & Scientific Scuba | C55: Maritime & Ports: 8 | D55: 8 | E55: carpenters; liuna | F55: carpenters-ictf; liuna-training-fund | G55: 4 | H55: 20 | I55: 20 | J55: channel-buoy-tender-pier; estuary-research-dock; north-shoreline-field-lab | K55: kelp-night-line-site; outfall-intake-lockout-site; pier-piling-inspection-station; pier-surface-supplied-station; shelf-checkout-site; trench-rov-station | L55: 95.4 | M55: =D55+ROW()/100000 -> 8.00055

Sheet Stations
A1: id | B1: app | C1: title | D1: category | E1: programmes | F1: steps | G1: kinds | H1: hazards | I1: interruptions | J1: citations | K1: evalScore | L1: standardsScore | M1: meshes
A2: abatement-chamber | B2: smartcity | C2: SmartCiti.X~ Abatement Chamber VR | D2: Water & Environmental | E2: hazmat-environmental | F2: 12 | G2: select; find; gauge; sequence; hold; track; drag | H2: 5 | I2: 0 | J2: 4 | K2: 90 | L2: 75 | M2: 113
A3: abatement-perimeter-awareness | B3: smartcity | C3: SmartCiti.X~ Abatement Perimeter Awareness VR | D3: Community Environmental Justice | E3: hunters-point-can-we-live | F3: 14 | G3: select; sequence; find; track; hold; gauge; turn; drag | H3: 4 | I3: 2 | J3: 4 | K3: 97 | L3: 100 | M3: 183
A4: aerial-ladder | B4: smartcity | C4: SmartCiti.X~ Aerial Ladder VR | D4: Emergency Services | E4: fall-protection | F4: 12 | G4: select; sequence; drag; gauge; turn; track; find | H4: 4 | I4: 2 | J4: 5 | K4: 94 | L4: 100 | M4: 167
A5: aerial-lashing | B5: smartcity | C5: SmartCiti.X~ Aerial Lashing VR | D5: Connectivity & Telecom | F5: 14 | G5: select; drag; hold; sequence; gauge; track; turn; find | H5: 4 | I5: 2 | J5: 7 | K5: 95 | L5: 100 | M5: 261
A6: aerosol-management | B6: smartcity | C6: SmartCiti.X~ Aerosol Management VR | D6: Dental & Oral Health | E6: dental-hygiene-unspoken-smiles | F6: 15 | G6: select; find; gauge; sequence; hold; drag; track | H6: 4 | I6: 2 | J6: 6 | K6: 96 | L6: 100 | M6: 164
A7: air-monitor | B7: smartcity | C7: SmartCiti.X~ Perimeter Air VR | D7: Environmental Monitoring | E7: air-quality-monitoring; hazmat-environmental; hunters-point-bay-restoration | F7: 10 | G7: select; sequence; gauge; hold; turn; find | H7: 4 | I7: 2 | J7: 3 | K7: 92 | L7: 67 | M7: 208
A8: air-network-data-qa | B8: smartcity | C8: SmartCiti.X~ Network Data Review VR | D8: Community Environmental Justice | E8: hunters-point-can-we-live | F8: 13 | G8: select; sequence; find; hold; gauge; track | H8: 4 | I8: 2 | J8: 3 | K8: 97 | L8: 100 | M8: 159
A9: air-sensor-install | B9: smartcity | C9: SmartCiti.X~ Neighbourhood Air Sensor VR | D9: Community Environmental Justice | E9: hunters-point-can-we-live | F9: 14 | G9: select; sequence; turn; find; hold; gauge; track | H9: 4 | I9: 2 | J9: 4 | K9: 93 | L9: 75 | M9: 213
A10: airport-ramp | B10: smartcity | C10: SmartCiti.X~ Airport Ramp VR | D10: Mobility & Transit | E10: situational-awareness; transit-ramp | F10: 11 | G10: select; find; sequence; track; gauge; drag | H10: 4 | I10: 2 | J10: 4 | K10: 96 | L10: 100 | M10: 180
A11: allergen-cocktail | B11: smartcity | C11: SmartCiti.X~ Allergens & Honest Drinks VR | D11: Culinary & Hospitality | E11: bartending-course | F11: 15 | G11: select; find; sequence; drag; hold; track | H11: 4 | I11: 2 | J11: 6 | K11: 93 | L11: 83 | M11: 166
A12: allergen-control | B12: smartcity | C12: SmartCiti.X~ Allergen Control VR | D12: Culinary & Hospitality | E12: culinary-kitchen | F12: 12 | G12: select; sequence; hold; find; drag; track | H12: 4 | I12: 2 | J12: 8 | K12: 93 | L12: 75 | M12: 150
A13: alteration-repair-ticket | B13: smartcity | C13: SmartCiti.X~ Alteration Repair Ticket VR | D13: Sewing & Garment Trades | E13: sewing-garment-trades | F13: 13 | G13: select; drag; gauge; sequence; track; hold; find | H13: 4 | I13: 2 | J13: 4 | K13: 97 | L13: 100 | M13: 152
A14: amalgam-waste-handling | B14: smartcity | C14: SmartCiti.X~ Amalgam Waste Handling VR | D14: Dental & Oral Health | E14: dental-hygiene-unspoken-smiles | F14: 15 | G14: turn; track; select; gauge; sequence; drag; find; hold | H14: 4 | I14: 2 | J14: 4 | K14: 96 | L14: 100 | M14: 163
A15: ambulance-scene-safety | B15: smartcity | C15: SmartCiti.X~ Ambulance Scene Safety VR | D15: Emergency Services | E15: first-responders | F15: 15 | G15: select; turn; sequence; drag; track; hold; find; gauge | H15: 4 | I15: 2 | J15: 6 | K15: 96 | L15: 100 | M15: 217
A16: ammonia-plant | B16: smartcity | C16: SmartCiti.X~ Ammonia Plant VR | D16: Building Systems & Facilities | F16: 16 | G16: select; turn; drag; gauge; sequence; find; track | H16: 4 | I16: 2 | J16: 9 | K16: 96 | L16: 100 | M16: 221
A17: apprenticeship-application-and-test | B17: smartcity | C17: SmartCiti.X~ Apprenticeship Application & Test VR | D17: Community Environmental Justice | E17: job-readiness-edition; wojrc-pathway-edition | F17: 12 | G17: select; find; sequence; hold; drag; turn; gauge; track | H17: 4 | I17: 2 | J17: 6 | K17: 98 | L17: 100 | M17: 188
A18: apprenticeship-standards-reading | B18: smartcity | C18: SmartCiti.X~ Reading an Apprenticeship Standard VR | D18: Community Environmental Justice | E18: job-readiness-edition; wojrc-pathway-edition | F18: 10 | G18: select; find; sequence | H18: 4 | I18: 0 | J18: 5 | K18: 88 | L18: 100 | M18: 0
A19: arc-flash-label-study | B19: smartcity | C19: SmartCiti.X~ Arc-Flash Label Study VR | D19: Energy & Power | E19: electrical-first-period | F19: 13 | G19: select; sequence; gauge; drag; find | H19: 4 | I19: 2 | J19: 5 | K19: 95 | L19: 100 | M19: 152
A20: arena-rigging | B20: smartcity | C20: SmartCiti.X~ Arena Rigging VR | D20: Entertainment & Live Events | F20: 14 | G20: select; sequence; gauge; drag; turn; track; hold; find | H20: 5 | I20: 2 | J20: 3 | K20: 96 | L20: 100 | M20: 270
A21: av-baggage-belt-loader-and-hold-loading | B21: smartcity | C21: SmartCiti.X~ Baggage Belt-Loader & Hold Loading VR | D21: Mobility & Transit | E21: aviation-maintenance-and-ground | F21: 15 | G21: sequence; select; find; drag; turn; track; gauge; hold | H21: 4 | I21: 2 | J21: 5 | K21: 96 | L21: 100 | M21: 168
A22: av-borescope-and-tool-control-inventory | B22: smartcity | C22: SmartCiti.X~ Borescope & Tool-Control Inventory VR | D22: Mobility & Transit | E22: aviation-maintenance-and-ground | F22: 15 | G22: sequence; select; gauge; drag; track; find; hold | H22: 4 | I22: 2 | J22: 6 | K22: 96 | L22: 100 | M22: 158
A23: av-deicing-truck-boom-operations | B23: smartcity | C23: SmartCiti.X~ De-icing Truck Boom Operations VR | D23: Mobility & Transit | E23: aviation-maintenance-and-ground | F23: 14 | G23: sequence; select; find; drag; turn; gauge; hold | H23: 4 | I23: 2 | J23: 7 | K23: 96 | L23: 100 | M23: 160
A24: av-ground-power-and-static-bonding-before-fuel | B24: smartcity | C24: SmartCiti.X~ Ground Power & Static Bonding Before Fuel VR | D24: Mobility & Transit | E24: aviation-maintenance-and-ground | F24: 14 | G24: sequence; select; find; drag; hold; track; gauge | H24: 4 | I24: 2 | J24: 7 | K24: 95 | L24: 100 | M24: 200
A25: av-hangar-jacking-and-stands | B25: smartcity | C25: SmartCiti.X~ Hangar Jacking & Stands VR | D25: Mobility & Transit | E25: aviation-maintenance-and-ground | F25: 15 | G25: sequence; select; find; track; turn; gauge; drag; hold | H25: 4 | I25: 2 | J25: 6 | K25: 95 | L25: 100 | M25: 183
A26: av-lavatory-and-potable-water-separation | B26: smartcity | C26: SmartCiti.X~ Lavatory & Potable Water Separation VR | D26: Mobility & Transit | E26: aviation-maintenance-and-ground | F26: 15 | G26: sequence; select; find; drag; turn; hold; track; gauge | H26: 4 | I26: 2 | J26: 5 | K26: 95 | L26: 100 | M26: 156
A27: av-marshalling-and-wingwalker-signals | B27: smartcity | C27: SmartCiti.X~ Marshalling & Wing-Walker Signals VR | D27: Mobility & Transit | E27: aviation-maintenance-and-ground | F27: 14 | G27: sequence; select; find; drag; track; hold; gauge | H27: 4 | I27: 2 | J27: 7 | K27: 95 | L27: 100 | M27: 191
A28: av-pushback-tug-and-towbar-connection | B28: smartcity | C28: SmartCiti.X~ Pushback Tug & Towbar Connection VR | D28: Mobility & Transit | E28: aviation-maintenance-and-ground | F28: 15 | G28: sequence; select; find; drag; hold; track; turn; gauge | H28: 4 | I28: 2 | J28: 6 | K28: 95 | L28: 100 | M28: 163
A29: backflow-test | B29: smartcity | C29: SmartCiti.X~ Backflow Test VR | D29: Water & Environmental | F29: 11 | G29: select; sequence; find; hold; turn; gauge; track | H29: 4 | I29: 2 | J29: 6 | K29: 95 | L29: 83 | M29: 164
A30: bakery-mixer | B30: smartcity | C30: SmartCiti.X~ Bakery Mixer VR | D30: Culinary & Hospitality | E30: culinary-kitchen | F30: 14 | G30: select; hold; turn; drag; gauge; track; find | H30: 4 | I30: 2 | J30: 7 | K30: 93 | L30: 86 | M30: 152
A31: ballast-water-sampling | B31: smartcity | C31: SmartCiti.X~ Ballast Water Sampling VR | D31: Maritime & Ports | E31: ports-maritime-ecology | F31: 13 | G31: select; turn; track; drag; hold; sequence; gauge; find | H31: 4 | I31: 2 | J31: 6 | K31: 97 | L31: 100 | M31: 214
A32: banquet-hot-hold | B32: smartcity | C32: SmartCiti.X~ Banquet Hot Hold VR | D32: Culinary & Hospitality | E32: culinary-kitchen; hotel-workers | F32: 14 | G32: select; turn; gauge; drag; sequence; track; find; hold | H32: 4 | I32: 2 | J32: 7 | K32: 95 | L32: 86 | M32: 212
A33: banquet-setup-lift | B33: smartcity | C33: SmartCiti.X~ Banquet Setup Lift VR | D33: Culinary & Hospitality | E33: hotel-workers | F33: 14 | G33: select; drag; hold; sequence; gauge; turn; find | H33: 4 | I33: 2 | J33: 4 | K33: 97 | L33: 100 | M33: 182
A34: bar-well-setup | B34: smartcity | C34: SmartCiti.X~ Opening the Well VR | D34: Culinary & Hospitality | E34: bartending-course | F34: 12 | G34: select; gauge; sequence; hold; drag; track; find | H34: 4 | I34: 2 | J34: 8 | K34: 95 | L34: 88 | M34: 162
A35: battery-storage-container-commissioning | B35: smartcity | C35: SmartCiti.X~ Battery Storage Container Commissioning VR | D35: Energy & Power | E35: energy-transition | F35: 15 | G35: select; find; gauge; sequence; drag; hold; turn; track | H35: 4 | I35: 2 | J35: 8 | K35: 97 | L35: 100 | M35: 229
A36: battery-yard | B36: smartcity | C36: SmartCiti.X~ Battery Yard VR | D36: Energy & Power | E36: electrical-first-period; energy-transition | F36: 12 | G36: select; sequence; hold; gauge; drag; find | H36: 4 | I36: 2 | J36: 5 | K36: 98 | L36: 100 | M36: 209
A37: bb-coach-feedback-and-growth-mindset | B37: smartcity | C37: SmartCiti.X~ Coach Feedback and Growth Mindset VR | D37: Youth Sports & Coaching | E37: basketball-fundamentals | F37: 14 | G37: find; select; hold; sequence; turn; gauge; drag; track | H37: 4 | I37: 2 | J37: 6 | K37: 96 | L37: 100 | M37: 201
A38: bb-composure-with-a-hostile-crowd-and-officials | B38: smartcity | C38: SmartCiti.X~ Composure with a Hostile Crowd and Officials VR | D38: Youth Sports & Coaching | E38: basketball-fundamentals | F38: 14 | G38: find; select; hold; sequence; turn; gauge; drag; track | H38: 4 | I38: 2 | J38: 6 | K38: 96 | L38: 100 | M38: 252
A39: bb-defensive-stance-and-closeouts | B39: smartcity | C39: SmartCiti.X~ Defensive Stance and Closeouts VR | D39: Youth Sports & Coaching | E39: basketball-fundamentals | F39: 14 | G39: find; select; sequence; hold; track; gauge; turn; drag | H39: 4 | I39: 2 | J39: 5 | K39: 97 | L39: 100 | M39: 223
A40: bb-dribble-moves-and-change-of-pace | B40: smartcity | C40: SmartCiti.X~ Dribble Moves and Change of Pace VR | D40: Youth Sports & Coaching | E40: basketball-fundamentals | F40: 14 | G40: find; select; sequence; gauge; turn; hold; track; drag | H40: 4 | I40: 2 | J40: 5 | K40: 95 | L40: 100 | M40: 170
A41: bb-final-possession-decision-under-pressure | B41: smartcity | C41: SmartCiti.X~ Final Possession, Decision Under Pressure VR | D41: Youth Sports & Coaching | E41: basketball-fundamentals | F41: 14 | G41: find; select; sequence; turn; hold; gauge; drag; track | H41: 4 | I41: 2 | J41: 6 | K41: 96 | L41: 100 | M41: 241
... A92: br-workboat-crane-lift-from-water | B92: smartcity | C92: SmartCiti.X~ Workboat Crane Lift From Water VR | D92: Maritime & Ports | E92: bay-restoration-maritime-underwater | F92: 14 | G92: sequence; select; find; turn; gauge; drag; track; hold | H92: 4 | I92: 2 | J92: 9 | K92: 97 | L92: 100 | M92: 182
A93: bridge-blast | B93: smartcity | C93: SmartCiti.X~ Bridge Blast VR | D93: Surface Prep & Coatings | F93: 15 | G93: select; drag; gauge; turn; sequence; track; find; hold | H93: 4 | I93: 2 | J93: 9 | K93: 95 | L93: 100 | M93: 246
A94: bridge-cable-inspection | B94: smartcity | C94: SmartCiti.X~ Bridge Cable Inspection VR | D94: Construction & Structural Trades | E94: bridge-and-structural | F94: 13 | G94: select; turn; find; track; gauge; drag; sequence | H94: 4 | I94: 2 | J94: 5 | K94: 94 | L94: 100 | M94: 172
A95: bridge-lead-containment | B95: smartcity | C95: SmartCiti.X~ Bridge Lead Containment VR | D95: Construction & Structural Trades | E95: bridge-and-structural | F95: 14 | G95: select; drag; sequence; turn; gauge; track; find; hold | H95: 4 | I95: 2 | J95: 8 | K95: 94 | L95: 100 | M95: 202
A96: broadcast-truck | B96: smartcity | C96: SmartCiti.X~ Broadcast Truck VR | D96: Entertainment & Live Events | F96: 14 | G96: select; turn; gauge; drag; sequence; hold; track; find | H96: 4 | I96: 2 | J96: 5 | K96: 96 | L96: 100 | M96: 220
A97: bs-bearing-replacement-and-jacking | B97: smartcity | C97: SmartCiti.X~ Bearing Replacement & Jacking VR | D97: Construction & Structural Trades | E97: bridge-and-structural | F97: 14 | G97: select; sequence; find; drag; track; gauge; hold; turn | H97: 4 | I97: 2 | J97: 6 | K97: 96 | L97: 100 | M97: 224
A98: bs-structural-bolting-and-torque | B98: smartcity | C98: SmartCiti.X~ Structural Bolting & Torque VR | D98: Construction & Structural Trades | E98: bridge-and-structural | F98: 14 | G98: select; find; gauge; sequence; turn; hold; track; drag | H98: 4 | I98: 2 | J98: 7 | K98: 97 | L98: 100 | M98: 280
A99: bs-tandem-lift-girder-set | B99: smartcity | C99: SmartCiti.X~ Tandem Lift & Girder Set VR | D99: Construction & Structural Trades | E99: bridge-and-structural | F99: 14 | G99: select; find; gauge; drag; sequence; track; hold; turn | H99: 4 | I99: 2 | J99: 9 | K99: 96 | L99: 100 | M99: 277
A100: bt-formwork-stripping-and-reshoring | B100: smartcity | C100: SmartCiti.X~ Formwork Stripping & Reshoring VR | D100: Construction & Structural Trades | E100: builders-trades | F100: 13 | G100: select; find; turn; hold; drag; gauge; sequence; track | H100: 4 | I100: 2 | J100: 6 | K100: 97 | L100: 100 | M100: 199
A101: bt-masonry-wall-layout-and-mortar | B101: smartcity | C101: SmartCiti.X~ Masonry Wall Layout & Mortar VR | D101: Construction & Structural Trades | E101: builders-trades | F101: 14 | G101: select; sequence; find; drag; gauge; hold; turn; track | H101: 4 | I101: 2 | J101: 6 | K101: 97 | L101: 100 | M101: 198
A102: bt-rebar-tying-and-impalement-protection | B102: smartcity | C102: SmartCiti.X~ Rebar Tying & Impalement Protection VR | D102: Construction & Structural Trades | E102: builders-trades | F102: 13 | G102: select; find; drag; sequence; gauge; hold; turn; track | H102: 4 | I102: 2 | J102: 7 | K102: 97 | L102: 100 | M102: 201
A103: budget-tradeoff-hearing | B103: smartcity | C103: SmartCiti.X~ Budget Tradeoff Hearing VR | D103: Community Environmental Justice | E103: civic-leadership-and-ei | F103: 13 | G103: find; turn; select; sequence; gauge; hold; drag; track | H103: 4 | I103: 2 | J103: 7 | K103: 98 | L103: 100 | M103: 228
A104: budget-with-irregular-income | B104: smartcity | C104: SmartCiti.X~ Budget With Irregular Income VR | D104: Community Environmental Justice | E104: job-readiness-edition; wojrc-pathway-edition | F104: 12 | G104: select; find; gauge; sequence; drag; hold; turn; track | H104: 4 | I104: 2 | J104: 6 | K104: 96 | L104: 100 | M104: 181
A105: building-rad-scan | B105: smartcity | C105: SmartCiti.X~ Building Rad Scan VR | D105: Environmental Monitoring | E105: hunters-point-bay-restoration | F105: 15 | G105: select; sequence; hold; gauge; track; turn; drag; find | H105: 4 | I105: 2 | J105: 5 | K105: 94 | L105: 100 | M105: 234
A106: bunkering-watch | B106: smartcity | C106: SmartCiti.X~ Bunkering Watch VR | D106: Maritime & Ports | E106: port-operations; ports-maritime-ecology | F106: 12 | G106: select; sequence; track; gauge; turn; find | H106: 4 | I106: 2 | J106: 7 | K106: 90 | L106: 100 | M106: 167
A107: bus-depot-lift | B107: smartcity | C107: SmartCiti.X~ Bus Depot Lift VR | D107: Mobility & Transit | E107: transit-ramp | F107: 10 | G107: select; sequence; gauge; drag; track; hold; find | H107: 4 | I107: 2 | J107: 5 | K107: 93 | L107: 80 | M107: 118
A108: bus-yard-fuelling-and-brake-check | B108: smartcity | C108: SmartCiti.X~ Bus Yard Fuelling & Brake Check VR | D108: Mobility & Transit | E108: transit-ramp | F108: 15 | G108: select; sequence; drag; hold; turn; find; gauge; track | H108: 4 | I108: 2 | J108: 9 | K108: 96 | L108: 89 | M108: 195
... A119: cardiac-arrest-pit-crew | B119: smartcity | C119: SmartCiti.X~ Cardiac Arrest — Pit Crew VR | D119: Emergency Services | E119: first-responders | F119: 14 | G119: find; sequence; track; turn; drag; hold; select; gauge | H119: 4 | I119: 2 | J119: 5 | K119: 96 | L119: 100 | M119: 230
A120: cath-lab | B120: smartcity | C120: SmartCiti.X~ Cath Lab VR | D120: Building Systems & Facilities | F120: 14 | G120: select; find; sequence; gauge; turn; hold; drag; track | H120: 4 | I120: 2 | J120: 6 | K120: 98 | L120: 100 | M120: 269
A121: cd-decompression-chamber-operations-and-post-dive | B121: smartcity | C121: SmartCiti.X~ Decompression Chamber Operations & Post-Dive VR | D121: Maritime & Ports | E121: commercial-diving-and-scientific-scuba | F121: 14 | G121: select; find; sequence; turn; drag; hold; track; gauge | H121: 4 | I121: 2 | J121: 10 | K121: 96 | L121: 100 | M121: 196
A122: cd-dive-records-and-incident-review | B122: smartcity | C122: SmartCiti.X~ Dive Records & Incident Review VR | D122: Maritime & Ports | E122: commercial-diving-and-scientific-scuba | F122: 13 | G122: select; find; sequence; track; drag; hold; gauge; turn | H122: 4 | I122: 2 | J122: 9 | K122: 96 | L122: 100 | M122: 205
A123: cd-hydraulic-tools-and-suction-hazards-underwater | B123: smartcity | C123: SmartCiti.X~ Hydraulic Tools & Suction Hazards Underwater VR | D123: Maritime & Ports | E123: commercial-diving-and-scientific-scuba | F123: 13 | G123: select; find; sequence; hold; turn; drag; track; gauge | H123: 4 | I123: 2 | J123: 11 | K123: 95 | L123: 100 | M123: 220
A124: cd-low-visibility-and-night-dive-line-work | B124: smartcity | C124: SmartCiti.X~ Low-Visibility & Night Dive Line Work VR | D124: Maritime & Ports | E124: commercial-diving-and-scientific-scuba | F124: 13 | G124: select; find; sequence; track; hold; drag; gauge; turn | H124: 4 | I124: 2 | J124: 9 | K124: 95 | L124: 100 | M124: 133
A125: cd-pier-piling-inspection-and-wrap-repair | B125: smartcity | C125: SmartCiti.X~ Pier Piling Inspection & Wrap Repair VR | D125: Maritime & Ports | E125: commercial-diving-and-scientific-scuba | F125: 14 | G125: select; track; find; hold; gauge; sequence; drag; turn | H125: 4 | I125: 2 | J125: 10 | K125: 95 | L125: 100 | M125: 156
A126: cd-rov-launch-recovery-and-tether-management | B126: smartcity | C126: SmartCiti.X~ ROV Launch, Recovery & Tether Management VR | D126: Maritime & Ports | E126: commercial-diving-and-scientific-scuba | F126: 15 | G126: select; find; sequence; drag; turn; hold; track; gauge | H126: 4 | I126: 2 | J126: 10 | K126: 94 | L126: 100 | M126: 248
A127: cd-scientific-scuba-buddy-check-and-lost-buddy-drill | B127: smartcity | C127: SmartCiti.X~ Scientific Scuba: Buddy Check & Lost-Buddy Drill VR | D127: Maritime & Ports | E127: commercial-diving-and-scientific-scuba | F127: 14 | G127: select; sequence; find; drag; track; hold; gauge; turn | H127: 4 | I127: 2 | J127: 8 | K127: 96 | L127: 100 | M127: 202
A128: cd-underwater-wet-welding-and-cutting | B128: smartcity | C128: SmartCiti.X~ Underwater Wet Welding & Cutting — Surface Side VR | D128: Maritime & Ports | E128: commercial-diving-and-scientific-scuba | F128: 14 | G128: select; find; drag; sequence; turn; hold; track; gauge | H128: 4 | I128: 2 | J128: 12 | K128: 96 | L128: 100 | M128: 216
A129: cell-site-battery | B129: smartcity | C129: SmartCiti.X~ Cell Site Battery VR | D129: Connectivity & Telecom | E129: energy-transition | F129: 11 | G129: select; sequence; turn; gauge; drag; hold; find | H129: 4 | I129: 2 | J129: 4 | K129: 98 | L129: 100 | M129: 170
A130: chain-hoist | B130: smartcity | C130: SmartCiti.X~ Chain Hoist VR | D130: Entertainment & Live Events | E130: live-events; rigging-lifting | F130: 10 | G130: select; gauge; sequence; hold; track; find | H130: 4 | I130: 2 | J130: 4 | K130: 95 | L130: 100 | M130: 118
A131: chairside-emergency | B131: smartcity | C131: SmartCiti.X~ Chairside Emergency VR | D131: Dental & Oral Health | E131: dental-hygiene-unspoken-smiles | F131: 12 | G131: find; sequence; hold; turn; select; track; drag | H131: 4 | I131: 2 | J131: 5 | K131: 97 | L131: 100 | M131: 159
A132: charge-point | B132: smartcity | C132: SmartCiti.X~ Charge Point VR | D132: Energy & Power | E132: electrical-first-period; energy-transition | F132: 11 | G132: select; sequence; turn; hold; gauge; drag | H132: 4 | I132: 2 | J132: 4 | K132: 97 | L132: 100 | M132: 198
... A143: cm-slab-screed-bull-float-and-trowel | B143: smartcity | C143: SmartCiti.X~ Slab Screed, Bull Float & Trowel VR | D143: Construction & Structural Trades | E143: cement-masons-and-plasterers | F143: 15 | G143: select; find; sequence; gauge; track; hold; turn; drag | H143: 4 | I143: 2 | J143: 7 | K143: 95 | L143: 100 | M143: 158
A144: cnc-cell | B144: smartcity | C144: SmartCiti.X~ CNC Cell VR | D144: Manufacturing & Automation | F144: 13 | G144: select; sequence; gauge; track; turn; drag; find | H144: 4 | I144: 2 | J144: 7 | K144: 98 | L144: 100 | M144: 178
A145: coalition-building-table | B145: smartcity | C145: SmartCiti.X~ Coalition Building Table VR | D145: Community Environmental Justice | E145: civic-leadership-and-ei | F145: 13 | G145: find; turn; select; hold; sequence; drag; gauge; track | H145: 4 | I145: 2 | J145: 7 | K145: 97 | L145: 100 | M145: 235
A146: community-listening-session | B146: smartcity | C146: SmartCiti.X~ Community Listening Session VR | D146: Community Environmental Justice | E146: civic-leadership-and-ei | F146: 13 | G146: find; drag; select; turn; hold; sequence; gauge; track | H146: 4 | I146: 2 | J146: 6 | K146: 97 | L146: 100 | M146: 278
A147: community-soil-split | B147: smartcity | C147: SmartCiti.X~ Community Soil Split VR | D147: Community Environmental Justice | E147: hunters-point-can-we-live | F147: 12 | G147: select; gauge; sequence; hold; drag; find | H147: 4 | I147: 2 | J147: 3 | K147: 98 | L147: 100 | M147: 173
A148: concrete-pour | B148: smartcity | C148: SmartCiti.X~ Concrete Pour VR | D148: Construction & Structural Trades | E148: builders-trades | F148: 12 | G148: select; find; sequence; gauge; track; hold; turn; drag | H148: 4 | I148: 2 | J148: 8 | K148: 97 | L148: 100 | M148: 190
A149: confined-rescue | B149: smartcity | C149: SmartCiti.X~ Confined Rescue VR | D149: Emergency Services | E149: confined-space; situational-awareness | F149: 11 | G149: select; hold; sequence; turn; gauge; track | H149: 4 | I149: 2 | J149: 6 | K149: 97 | L149: 100 | M149: 157
A150: conflict-mediation-room | B150: smartcity | C150: SmartCiti.X~ Conflict Mediation Room VR | D150: Community Environmental Justice | E150: civic-leadership-and-ei | F150: 13 | G150: find; select; turn; sequence; hold; drag; gauge; track | H150: 4 | I150: 2 | J150: 6 | K150: 97 | L150: 100 | M150: 191
A151: constituent-service-desk | B151: smartcity | C151: SmartCiti.X~ Constituent Service Desk VR | D151: Community Environmental Justice | E151: civic-leadership-and-ei | F151: 14 | G151: find; select; hold; sequence; drag; gauge; turn; track | H151: 4 | I151: 2 | J151: 7 | K151: 98 | L151: 100 | M151: 199
A152: container-lashing | B152: smartcity | C152: SmartCiti.X~ Container Lashing VR | D152: Maritime & Ports | E152: bay-area-union-edition; port-operations; ports-maritime-ecology | F152: 11 | G152: select; sequence; hold; gauge; turn; find | H152: 5 | I152: 2 | J152: 5 | K152: 97 | L152: 100 | M152: 242
A153: conveyor-guard | B153: smartcity | C153: SmartCiti.X~ Conveyor Guard VR | D153: Manufacturing & Automation | F153: 11 | G153: select; turn; hold; drag; find; gauge | H153: 4 | I153: 2 | J153: 5 | K153: 96 | L153: 100 | M153: 155
A154: cooling-tower | B154: smartcity | C154: SmartCiti.X~ Cooling Tower VR | D154: Building Systems & Facilities | E154: stationary-engineer | F154: 11 | G154: select; sequence; turn; hold; find; gauge; track | H154: 4 | I154: 2 | J154: 8 | K154: 93 | L154: 56 | M154: 186
A155: crane-yard | B155: smartcity | C155: SmartCiti.X~ Crane Yard VR | D155: Construction & Structural Trades | E155: rigging-lifting; situational-awareness | F155: 15 | G155: select; sequence; gauge; hold; track; drag | H155: 4 | I155: 2 | J155: 6 | K155: 91 | L155: 100 | M155: 121
A156: credit-report-reading | B156: smartcity | C156: SmartCiti.X~ Credit Report Reading VR | D156: Community Environmental Justice | E156: job-readiness-edition; wojrc-pathway-edition | F156: 12 | G156: select; find; hold; gauge; sequence; drag; turn; track | H156: 4 | I156: 2 | J156: 5 | K156: 96 | L156: 100 | M156: 189
A157: creosote-pile-removal | B157: smartcity | C157: SmartCiti.X~ Creosote Pile Removal VR | D157: Maritime & Ports | E157: hunters-point-bay-restoration | F157: 13 | G157: select; sequence; drag; find; turn; track; gauge; hold | H157: 4 | I157: 2 | J157: 8 | K157: 96 | L157: 100 | M157: 241
A158: crisis-communication-podium | B158: smartcity | C158: SmartCiti.X~ Crisis Communication Podium VR | D158: Community Environmental Justice | E158: civic-leadership-and-ei | F158: 13 | G158: find; select; turn; sequence; gauge; hold; drag; track | H158: 4 | I158: 2 | J158: 6 | K158: 98 | L158: 100 | M158: 211
A159: crisis-intervention-call | B159: smartcity | C159: SmartCiti.X~ Crisis Intervention Call VR | D159: Emergency Services | E159: first-responders | F159: 15 | G159: find; gauge; turn; select; track; sequence; hold; drag | H159: 4 | I159: 2 | J159: 8 | K159: 95 | L159: 100 | M159: 263
A160: crisis-line-shift | B160: smartcity | C160: SmartCiti.X~ Crisis Line Shift VR | D160: Emergency Services | E160: first-responders | F160: 14 | G160: drag; find; select; sequence; track; hold; gauge; turn | H160: 5 | I160: 2 | J160: 8 | K160: 96 | L160: 100 | M160: 185
A161: critical-incident-debrief | B161: smartcity | C161: SmartCiti.X~ Critical Incident Debrief VR | D161: Emergency Services | E161: first-responders | F161: 15 | G161: find; gauge; turn; drag; select; sequence; track; hold | H161: 4 | I161: 2 | J161: 9 | K161: 94 | L161: 89 | M161: 193
A162: cs-non-entry-retrieval-and-tripod | B162: smartcity | C162: SmartCiti.X~ Non-Entry Retrieval & Tripod VR | D162: Water & Environmental | E162: confined-space | F162: 14 | G162: select; find; drag; sequence; hold; track; turn | H162: 4 | I162: 2 | J162: 9 | K162: 97 | L162: 100 | M162: 200
A163: cs-permit-entry-and-attendant-duties | B163: smartcity | C163: SmartCiti.X~ Permit Entry & Attendant Duties VR | D163: Water & Environmental | E163: confined-space | F163: 13 | G163: select; find; sequence; gauge; drag; track; hold | H163: 4 | I163: 2 | J163: 9 | K163: 98 | L163: 100 | M163: 224
A164: cs-ventilation-and-air-monitoring-plan | B164: smartcity | C164: SmartCiti.X~ Ventilation & Air Monitoring Plan VR | D164: Water & Environmental | E164: confined-space | F164: 14 | G164: select; find; drag; turn; sequence; hold; gauge; track | H164: 4 | I164: 2 | J164: 8 | K164: 97 | L164: 100 | M164: 200
A165: cutoff-overservice | B165: smartcity | C165: SmartCiti.X~ Cut-Off / Overservice VR | D165: Culinary & Hospitality | E165: bartending-course | F165: 14 | G165: select; find; gauge; turn; hold; sequence; drag | H165: 4 | I165: 2 | J165: 6 | K165: 93 | L165: 83 | M165: 179
... A216: ethics-and-conflict-of-interest | B216: smartcity | C216: SmartCiti.X~ Ethics and Conflict of Interest VR | D216: Community Environmental Justice | E216: civic-leadership-and-ei | F216: 13 | G216: find; select; gauge; drag; turn; sequence; hold; track | H216: 4 | I216: 2 | J216: 7 | K216: 97 | L216: 100 | M216: 188
A217: ev-extrication | B217: smartcity | C217: SmartCiti.X~ EV Extrication VR | D217: Emergency Services | F217: 15 | G217: select; drag; sequence; turn; hold; track; gauge; find | H217: 4 | I217: 2 | J217: 3 | K217: 92 | L217: 100 | M217: 244
A218: ew-car-top-inspection-station-and-ride | B218: smartcity | C218: SmartCiti.X~ Car Top Inspection Station and Ride VR | D218: Building Systems & Facilities | E218: elevator-constructors | F218: 14 | G218: select; gauge; find; turn; track; sequence | H218: 4 | I218: 2 | J218: 3 | K218: 95 | L218: 100 | M218: 152
A219: ew-door-operator-adjustment-and-gap | B219: smartcity | C219: SmartCiti.X~ Door Operator Adjustment and Gap VR | D219: Building Systems & Facilities | E219: elevator-constructors | F219: 13 | G219: select; turn; gauge; find; hold; sequence | H219: 4 | I219: 2 | J219: 3 | K219: 95 | L219: 100 | M219: 140
A220: ew-elevator-entrapment-and-rescue-with-fire-service | B220: smartcity | C220: SmartCiti.X~ Elevator Entrapment and Rescue with Fire Service VR | D220: Building Systems & Facilities | E220: elevator-constructors | F220: 15 | G220: select; find; gauge; turn; track; drag; sequence | H220: 4 | I220: 2 | J220: 3 | K220: 95 | L220: 100 | M220: 168
...

Sheet Assets
A1: name | B1: family | C1: build | D1: meshes | E1: footprint | F1: parts | G1: note | H1: stationCount | I1: stations | J1: unity | K1: source
A2: excavator | B2: equipment | C2: excavator | D2: 21 | E2: 3.05 x 4.83 x 10.78 | F2: trackL; trackR; house; door; boom; stick; bucket; lights; counterweight | G2: 20 t tracked excavator, dig-ready | H2: 8 | I2: br-barge-loading-of-contaminated-sediment; br-culvert-retrofit-for-fish-passage; br-dredge-material-screening-and-disposal-decision; br-dredge-spoils-dewatering-pad; br-legacy-mercury-and-pcb-hotspot-handling; br-turbidity-curtain-deployment; br-water-quality-sonde-calibration-and-deploy; op-excavator-trench-and-utility-locate | J2: yes | K2: WebXR/shared/equipment.js EQUIPMENT_BUDGET
A3: amphibiousExcavator | B3: equipment | C3: amphibiousExcavator | D3: 22 | E3: 4.65 x 5.21 x 10.81 | F3: pontoonL; pontoonR; house; door; boom; stick; bucket; lights; counterweight | G3: amphibious pontoon excavator, dig-ready | H3: 2 | I3: br-bird-nesting-buffer-and-work-window; br-tidal-marsh-grading-amphibious-excavator | J3: yes | K3: WebXR/shared/equipment.js EQUIPMENT_BUDGET
A4: backhoe | B4: equipment | C4: backhoe | D4: 23 | E4: 2.36 x 3.75 x 7.46 | F4: loaderArms; loaderBucket; swingFrame; boom; stick; bucket; stabilizers; wheels; door; lights | G4: loader backhoe, travel pose | H4: 1 | I4: op-equipment-daily-walkaround-and-fluids | J4: yes | K4: WebXR/shared/equipment.js EQUIPMENT_BUDGET
A5: skidSteer | B5: equipment | C5: skidSteer | D5: 12 | E5: 1.83 x 2.07 x 3.31 | F5: arms; bucket; wheelsL; wheelsR; wheels; door; lights | G5: wheeled skid steer | H5: 2 | I5: bt-rebar-tying-and-impalement-protection; ut-service-line-locate-and-hand-dig-near-gas-main | J5: yes | K5: WebXR/shared/equipment.js EQUIPMENT_BUDGET
A6: dumpTruck | B6: equipment | C6: dumpTruck | D6: 20 | E6: 3.02 x 3.26 x 9.57 | F6: bed; tailgate; hoist; doorL; doorR; mirrorL; mirrorR; wheels; lights | G6: tri-axle dump truck | H6: 3 | I6: br-legacy-mercury-and-pcb-hotspot-handling; mm-haul-truck-berm; op-loader-truck-loading-and-blind-spots | J6: yes | K6: WebXR/shared/equipment.js EQUIPMENT_BUDGET
A7: mobileCrane | B7: equipment | C7: mobileCrane | D7: 27 | E7: 2.96 x 3.49 x 11.46 | F7: outriggers; house; counterweight; cabDoor; boom; boomSections; hook; wheels; lights | G7: rough-terrain crane, travel pose | H7: 4 | I7: br-trash-capture-device-service; bs-tandem-lift-girder-set; gl-glass-handling-cart-and-crane-vacuum-lifter; rl-critical-lift-plan-and-signalperson | J7: yes | K7: WebXR/shared/equipment.js EQUIPMENT_BUDGET
A8: aerialBoomLift | B8: equipment | C8: aerialBoomLift | D8: 19 | E8: 2.42 x 2.61 x 9 | F8: turntable; boom; boomTele; jib; platform; controls; groundControls; wheels; beacon | G8: 60 ft telescopic boom lift, stowed | H8: 2 | I8: bs-tandem-lift-girder-set; fp-anchor-selection-and-rescue-plan | J8: yes | K8: WebXR/shared/equipment.js EQUIPMENT_BUDGET
A9: scissorLift | B9: equipment | C9: scissorLift | D9: 15 | E9: 1.16 x 2.34 x 2.3 | F9: scissors; platform; extensionDeck; controls; gate; potholeGuards; wheels; beacon | G9: 26 ft slab scissor, stowed | H9: 2 | I9: le-followspot-and-truss-access-at-height; tw-high-bay-order-picker-fall-protection | J9: yes | K9: WebXR/shared/equipment.js EQUIPMENT_BUDGET
A10: compactor | B10: equipment | C10: compactor | D10: 14 | E10: 2.4 x 3.12 x 5.68 | F10: frontFrame; drum; wheels; rops; seat; controls; lights; beacon | G10: single-drum soil compactor | H10: 2 | I10: cm-curb-and-gutter-forms-and-finish; op-compactor-lift-thickness-and-edge | J10: yes | K10: WebXR/shared/equipment.js EQUIPMENT_BUDGET
A11: generatorTrailer | B11: equipment | C11: generatorTrailer | D11: 14 | E11: 1.9 x 2.41 x 4.54 | F11: doorL; doorR; controlPanel; eStop; wheels; jack; lights | G11: towable diesel generator | H11: 4 | I11: br-surface-supplied-dive-station-setup; cs-ventilation-and-air-monitoring-plan; le-crowd-barricade-and-show-stop-call; ut-night-storm-response-crew-and-portable-generator | J11: yes | K11: WebXR/shared/equipment.js EQUIPMENT_BUDGET
A12: lightTower | B12: equipment | C12: lightTower | D12: 17 | E12: 2.34 x 9.29 x 3.49 | F12: mast; mastUpper; lamps; outriggers; controlPanel; wheels; jack | G12: towable light tower, raised | H12: 1 | I12: le-crowd-barricade-and-show-stop-call | J12: yes | K12: WebXR/shared/equipment.js EQUIPMENT_BUDGET
A13: lightTower:stowed | B13: equipment | C13: lightTower | D13: 17 | E13: 1.58 x 1.77 x 4.81 | F13: mast; mastUpper; lamps; outriggers; controlPanel; wheels; jack | G13: towable light tower, stowed for tow | H13: 1 | I13: le-crowd-barricade-and-show-stop-call | J13: yes | K13: WebXR/shared/equipment.js EQUIPMENT_BUDGET
... A52: ambulance | B52: vehicle | C52: ambulance | D52: 25 | E52: 2.62 x 3.13 x 7.06 | F52: doorL; doorR; doorSide; doorRearL; doorRearR; compartments; warningLights; wheels; mirrorL; mirrorR; lights | G52: Type III, generic markings, rear chevrons | H52: 2 | I52: firefighter-rehab-sector; hz-decon-corridor-for-a-mass-casualty-drill | J52: yes | K52: WebXR/shared/fleet.js FLEET_BUDGET
A53: fireEngine | B53: vehicle | C53: fireEngine | D53: 28 | E53: 3.2 x 3.23 x 10.25 | F53: doorL; doorR; doorCrewL; doorCrewR; pumpPanel; pumpControls; hoseBed; ladder; compartments; warningLights; wheels; mirrorL; mirrorR; lights | G53: pumper: pump panel, hose bed, roof ladders | H53: 0 | J53: yes | K53: WebXR/shared/fleet.js FLEET_BUDGET
A54: bucketTruck | B54: vehicle | C54: bucketTruck | D54: 32 | E54: 3.3 x 3.44 x 9.6 | F54: doorL; doorR; mirrorL; mirrorR; wheels; lights; turret; boom; boomUpper; bucket; outriggers; compartments; controls | G54: insulated aerial device, articulated turret-boom-bucket | H54: 0 | J54: yes | K54: WebXR/shared/fleet.js FLEET_BUDGET
A55: busTransit | B55: vehicle | C55: busTransit | D55: 16 | E55: 3.3 x 3.26 x 12.42 | F55: doorFront; doorRear; destinationSign; wheels; mirrorL; mirrorR; lights | G55: 40 ft low-floor | H55: 2 | I55: bus-depot-lift; tr-wheelchair-lift-and-securement-on-a-bus | J55: yes | K55: WebXR/shared/fleet.js FLEET_BUDGET
A56: schoolBus | B56: vehicle | C56: schoolBus | D56: 33 | E56: 3.16 x 3.1 x 10.79 | F56: doorEntry; doorRear; mirrorL; mirrorR; crossviewMirror; wheels; lights; stopArm; crossingGate; warningLights | G56: Type C conventional, 35 ft, 8-way warning lights, stop arm and crossing gate | H56: 1 | I56: ed-bus-pretrip-and-loading-zone | J56: yes | K56: WebXR/shared/fleet.js FLEET_BUDGET
A57: forkliftCounterbalance | B57: vehicle | C57: forkliftCounterbalance | D57: 21 | E57: 1.12 x 2.28 x 3.57 | F57: mast; innerMast; carriage; forks; overheadGuard; counterweight; lpgTank; seat; controls; beacon; wheels; lights | G57: 5,000 lb LPG counterbalance | H57: 9 | I57: drive-backing-serpentine-and-alley-dock; drive-light-vehicle-fleet-and-forklift-course; forklift-dock; hz-drum-staging-and-compatibility-segregation; ml-mail-handler-forklift-and-container-dock; tdl-trailer-loading-and-dock-plate; tw-battery-change-and-charging-bay-safety; tw-cold-storage-ppe-and-rotation; tw-dock-leveler-and-trailer-restraint-check | J57: yes | K57: WebXR/shared/fleet.js FLEET_BUDGET
A58: yardHustler | B58: vehicle | C58: yardHustler | D58: 19 | E58: 2.91 x 3.43 x 5.61 | F58: doorL; doorRear; mirrorL; mirrorR; wheels; fifthWheel; gladHandService; gladHandEmergency; beacon; lights | G58: terminal tractor, lifting fifth wheel | H58: 4 | I58: ml-delivery-van-pretrip-and-route-loading; po-yard-hostler-and-pedestrian-separation; tdl-pretrip-inspection; tdl-trailer-loading-and-dock-plate | J58: yes | K58: WebXR/shared/fleet.js FLEET_BUDGET
A59: workboat | B59: boat | C59: workboat | D59: 16 | E59: 3.15 x 3.45 x 8.18 | F59: wheelhouseDoor; outboards; davit; navLights; portLight; starboardLight; mastheadLight | G59: 7.6 m aluminium workboat | H59: 16 | I59: br-benthic-grab-and-invertebrate-sorting; br-boom-towing-between-two-vessels; br-cold-water-immersion-and-mob-recovery; br-dive-site-hazard-assessment-and-jsa; br-dive-tender-and-umbilical-management; br-dredge-material-screening-and-disposal-decision; br-hyperbaric-chamber-standby; br-marine-mammal-observer-during-pile-driving; br-sediment-chain-of-custody-and-lab-prep; br-surface-supplied-dive-station-setup; br-turbidity-curtain-deployment; br-vhf-and-navigation-in-a-work-zone; br-water-quality-sonde-calibration-and-deploy; br-workboat-crane-lift-from-water; cd-rov-launch-recovery-and-tether-management; me-water-column-sampling-from-a-small-boat | J59: yes | K59: WebXR/shared/fleet.js FLEET_BUDGET
A60: motorYacht | B60: boat | C60: motorYacht | D60: 35 | E60: 6.72 x 8.01 x 24.23 | F60: saloonDoor; helm; bowCleats; springCleats; sternCleats; fuelFill; shorePowerInlet; engineHatch; davit; tender; fenders; lifeRing; navLights; portLight; starboardLight; mastheadLight; sternLight | G60: 24 m motor yacht: flybridge, swim platform, tender in a davit, shore-power inlet | H60: 6 | I60: yc-fuel-dock-transfer-and-spill-kit; yc-line-handling-and-docking-in-crosswind; yc-man-overboard-recovery-drill; yc-pre-departure-safety-briefing-and-guest-count; yc-shore-power-connection-and-in-water-electrical-safety; yc-tender-launch-and-guest-transfer | J60: yes | K60: WebXR/shared/fleet.js FLEET_BUDGET
A61: yachtTender | B61: boat | C61: yachtTender | D61: 15 | E61: 1.89 x 1.52 x 4.55 | F61: outboard; killCord; console; bowEye; sternCleat; fuelTank; navLight | G61: 4.2 m rigid inflatable tender with an outboard and a kill-cord | H61: 1 | I61: yc-tender-launch-and-guest-transfer | J61: yes | K61: WebXR/shared/fleet.js FLEET_BUDGET
A62: skiff | B62: boat | C62: skiff | D62: 17 | E62: 2.11 x 1.79 x 5.69 | F62: outboard; console; killSwitch; bowCleat; sternCleat; navLights; portLight; starboardLight; sternLight | G62: 5.2 m aluminium centre-console skiff | H62: 13 | I62: br-beach-seine-fish-survey-and-handling; br-bird-nesting-buffer-and-work-window; br-boom-towing-between-two-vessels; br-cold-water-immersion-and-mob-recovery; br-debris-skimmer-vessel-operations; br-derelict-vessel-salvage-rigging; br-drone-shoreline-survey; br-marine-mammal-observer-during-pile-driving; br-vhf-and-navigation-in-a-work-zone; br-volunteer-cleanup-day-safety-lead; cd-scientific-scuba-buddy-check-and-lost-buddy-drill; me-eelgrass-seed-collection-and-nursery; me-oyster-reef-monitoring-and-settlement-tiles | J62: yes | K62: WebXR/shared/fleet.js FLEET_BUDGET
A63: deckBarge | B63: boat | C63: deckBarge | D63: 13 | E63: 6.24 x 2.7 x 16 | F63: bitts; ladder | G63: 16 m flat steel deck barge, raked ends | H63: 2 | I63: br-barge-loading-of-contaminated-sediment; br-vhf-and-navigation-in-a-work-zone | J63: yes | K63: WebXR/shared/fleet.js FLEET_BUDGET
A64: deckBarge:hopper | B64: boat | C64: deckBarge | D64: 16 | E64: 6.24 x 3.1 x 16 | F64: bitts; ladder; coaming; liner; load | G64: deck barge with a lined sediment hopper | H64: 2 | I64: br-barge-loading-of-contaminated-sediment; br-vhf-and-navigation-in-a-work-zone | J64: yes | K64: WebXR/shared/fleet.js FLEET_BUDGET
A65: salvageCraneBarge | B65: boat | C65: salvageCraneBarge | D65: 30 | E65: 7.24 x 13.59 x 18 | F65: house; boom; hook; hoistLine; counterweight; cabDoor; spuds; bitts; ladder | G65: 18 m spud barge with a revolving lattice-boom crane | H65: 2 | I65: br-derelict-vessel-salvage-rigging; br-marine-mammal-observer-during-pile-driving | J65: yes | K65: WebXR/shared/fleet.js FLEET_BUDGET
A66: skimmerVessel | B66: boat | C66: skimmerVessel | D66: 20 | E66: 4.22 x 4.1 x 12.21 | F66: conveyor; basket; sweepArms; tankHatch; wheelhouseDoor; navLights; portLight; starboardLight; mastheadLight | G66: 11 m catamaran debris and oil skimmer | H66: 1 | I66: br-debris-skimmer-vessel-operations | J66: yes | K66: WebXR/shared/fleet.js FLEET_BUDGET
... A70: rov | B70: boat | C70: rov | D70: 9 | E70: 0.62 x 0.55 x 1.01 | F70: thrusters; camera; lights; manipulator; tetherPoint | G70: observation-class ROV, four thrusters, camera dome, manipulator | H70: 1 | I70: cd-rov-launch-recovery-and-tether-management | J70: yes | K70: WebXR/shared/fleet.js FLEET_BUDGET
A71: jerseyBarrier | B71: prop | C71: jerseyBarrier | D71: 1 | E71: 0.61 x 0.81 x 3.05 | G71: concrete F-shape traffic barrier, 10 ft run | H71: 0 | J71: no | K71: WebXR/shared/props.js PROPS_BUDGET
A72: waterBarrier | B72: prop | C72: waterBarrier | D72: 2 | E72: 0.5 x 0.79 x 1.83 | G72: plastic water/sand-filled lane barrier | H72: 1 | I72: md-location-shoot-traffic-control-and-heat-hydration | J72: no | K72: WebXR/shared/props.js PROPS_BUDGET
A73: coneCluster | B73: prop | C73: coneCluster | D73: 9 | E73: 1 x 0.71 x 0.84 | G73: three traffic cones in a triangle | H73: 1 | I73: md-location-shoot-traffic-control-and-heat-hydration | J73: no | K73: WebXR/shared/props.js PROPS_BUDGET
A74: lightMast | B74: prop | C74: lightMast | D74: 10 | E74: 1.3 x 9 x 0.5 | F74: lamps | G74: fixed site light mast, four heads, lit at night | H74: 0 | J74: no | K74: WebXR/shared/props.js PROPS_BUDGET
A75: portableToilet | B75: prop | C75: portableToilet | D75: 4 | E75: 1.26 x 2.32 x 1.26 | F75: door | G75: single-unit portable toilet | H75: 0 | J75: no | K75: WebXR/shared/props.js PROPS_BUDGET
A76: siteOffice | B76: prop | C76: siteOffice | D76: 6 | E76: 2.45 x 3.1 x 6.49 | F76: door | G76: 20 ft portable site office | H76: 2 | I76: cd-dive-records-and-incident-review; md-location-shoot-traffic-control-and-heat-hydration | J76: no | K76: WebXR/shared/props.js PROPS_BUDGET
A77: dumpster | B77: prop | C77: dumpster | D77: 4 | E77: 1.37 x 1.26 x 1.83 | F77: lidL; lidR | G77: front-load construction dumpster | H77: 4 | I77: op-equipment-daily-walkaround-and-fluids; op-excavator-trench-and-utility-locate; op-loader-truck-loading-and-blind-spots; tw-conveyor-jam-clearing-and-loto | J77: no | K77: WebXR/shared/props.js PROPS_BUDGET
A78: scaffoldTower | B78: prop | C78: scaffoldTower | D78: 14 | E78: 1.4 x 4 x 1.4 | G78: two-lift scaffold tower with platform and guardrail | H78: 1 | I78: av-hangar-jacking-and-stands | J78: no | K78: WebXR/shared/props.js PROPS_BUDGET
A79: palletStack | B79: prop | C79: palletStack | D79: 4 | E79: 1.04 x 1.7 x 1.24 | G79: three loaded pallets under shrink film | H79: 12 | I79: av-baggage-belt-loader-and-hold-loading; ml-flat-sorter-guarding-and-lockout; ml-mail-handler-forklift-and-container-dock; ml-parcel-sorter-conveyor-jam-and-loto; ml-suspicious-package-protocol; tw-amr-traffic-zone-entry-and-lockout; tw-cold-storage-ppe-and-rotation; tw-conveyor-jam-clearing-and-loto; tw-dock-leveler-and-trailer-restraint-check; tw-high-bay-order-picker-fall-protection; tw-palletizer-cell-fenced-access-permit; tw-pick-to-light-ergonomics-and-rotation | J79: no | K79: WebXR/shared/props.js PROPS_BUDGET
A80: cableSpool | B80: prop | C80: cableSpool | D80: 3 | E80: 0.9 x 1.5 x 1.5 | G80: wound cable reel, standing on its rim | H80: 3 | I80: op-compactor-lift-thickness-and-edge; op-dozer-slope-work-and-rollover-protection; op-excavator-trench-and-utility-locate | J80: no | K80: WebXR/shared/props.js PROPS_BUDGET
A81: fireHydrant | B81: prop | C81: fireHydrant | D81: 6 | E81: 0.38 x 0.78 x 0.46 | G81: dry-barrel fire hydrant | H81: 1 | I81: ut-hydrant-flow-test-and-flushing-with-traffic-control | J81: no | K81: WebXR/shared/props.js PROPS_BUDGET
A82: bollardRow | B82: prop | C82: bollardRow | D82: 10 | E82: 6.16 x 1.08 x 0.16 | G82: row of five steel bollards | H82: 0 | J82: no | K82: WebXR/shared/props.js PROPS_BUDGET
A83: parkBench | B83: prop | C83: parkBench | D83: 7 | E83: 1.8 x 0.94 x 0.5 | G83: slatted park bench | H83: 1 | I83: gk-string-trimmer-and-blower-ppe-and-bystander-zone | J83: no | K83: WebXR/shared/props.js PROPS_BUDGET
A84: streetTree:small | B84: prop | C84: streetTree | D84: 5 | E84: 2.48 x 4.46 x 2.4 | G84: young street tree in a tree grate | H84: 1 | I84: gk-tree-work-pole-saw-and-drop-zone | J84: no | K84: WebXR/shared/props.js PROPS_BUDGET
A85: streetTree:medium | B85: prop | C85: streetTree | D85: 5 | E85: 3.93 x 6.52 x 3.8 | G85: established street tree in a tree grate | H85: 1 | I85: gk-tree-work-pole-saw-and-drop-zone | J85: no | K85: WebXR/shared/props.js PROPS_BUDGET
A86: streetTree:large | B86: prop | C86: streetTree | D86: 5 | E86: 5.8 x 9.02 x 5.6 | G86: mature street tree in a tree grate | H86: 1 | I86: gk-tree-work-pole-saw-and-drop-zone | J86: no | K86: WebXR/shared/props.js PROPS_BUDGET
A87: shrubBed | B87: prop | C87: shrubBed | D87: 6 | E87: 2.3 x 0.72 x 1 | G87: curbed planting bed, five shrubs | H87: 2 | I87: gk-pesticide-and-fertilizer-application-per-the-label; gk-ride-on-mower-pre-start-and-slope-work | J87: no | K87: WebXR/shared/props.js PROPS_BUDGET
A88: fencePanel | B88: prop | C88: fencePanel | D88: 5 | E88: 3.05 x 1.9 x 0.07 | G88: 10 ft chain-link fence panel | H88: 3 | I88: op-dozer-slope-work-and-rollover-protection; op-grader-fine-grade-and-crown; tw-palletizer-cell-fenced-access-permit | J88: no | K88: WebXR/shared/props.js PROPS_BUDGET
A89: fencePanel:gate | B89: prop | C89: fencePanelGate | D89: 6 | E89: 3.05 x 1.9 x 0.07 | F89: gate | G89: chain-link fence panel with a swinging gate leaf | H89: 2 | I89: ed-playground-equipment-inspection; tw-palletizer-cell-fenced-access-permit | J89: no | K89: WebXR/shared/props.js PROPS_BUDGET
A90: shippingContainer | B90: prop | C90: shippingContainer | D90: 5 | E90: 2.44 x 2.65 x 6.06 | F90: doorL; doorR | G90: 20 ft ISO shipping container, oxide red | H90: 2 | I90: ml-mail-handler-forklift-and-container-dock; op-pile-driving-rig-and-lead-setup | J90: no | K90: WebXR/shared/props.js PROPS_BUDGET
A91: shippingContainer:blue | B91: prop | C91: shippingContainer | D91: 5 | E91: 2.44 x 2.65 x 6.06 | F91: doorL; doorR | G91: 20 ft ISO shipping container, marine blue | H91: 2 | I91: ml-mail-handler-forklift-and-container-dock; op-pile-driving-rig-and-lead-setup | J91: no | K91: WebXR/shared/props.js PROPS_BUDGET
A92: fuelTank | B92: prop | C92: fuelTank | D92: 4 | E92: 2.2 x 1.38 x 1.16 | F92: gauge | G92: skid fuel tank on a twin saddle stand | H92: 1 | I92: op-equipment-daily-walkaround-and-fluids | J92: no | K92: WebXR/shared/props.js PROPS_BUDGET
A93: generatorSkid | B93: prop | C93: generatorSkid | D93: 6 | E93: 1 x 1.34 x 2.2 | F93: stack; controlPanel | G93: diesel generator on a skid | H93: 0 | J93: no | K93: WebXR/shared/props.js PROPS_BUDGET
A94: counterweightStack | B94: prop | C94: counterweightStack | D94: 5 | E94: 2.5 x 1.5 x 1 | G94: mobile crane counterweight, five slabs | H94: 1 | I94: op-crawler-crane-assembly-and-load-chart | J94: no | K94: WebXR/shared/props.js PROPS_BUDGET
A95: picnicTable | B95: prop | C95: picnicTable | D95: 5 | E95: 1.6 x 0.9 x 1.5 | G95: A-frame picnic table | H95: 0 | J95: no | K95: WebXR/shared/props.js PROPS_BUDGET
A96: aircraftJack | B96: prop | C96: aircraftJack | D96: 5 | E96: 0.78 x 1.2 x 0.8 | F96: ram; saddle | G96: tripod aircraft jack, ram extended | H96: 1 | I96: av-hangar-jacking-and-stands | J96: no | K96: WebXR/shared/props.js PROPS_BUDGET
A97: palletRackBay | B97: prop | C97: palletRackBay | D97: 5 | E97: 2.62 x 4.22 x 1.18 | G97: selective pallet-rack bay, two loaded levels and a rating plaque | H97: 8 | I97: ml-flat-sorter-guarding-and-lockout; ml-parcel-sorter-conveyor-jam-and-loto; ml-suspicious-package-protocol; tw-amr-traffic-zone-entry-and-lockout; tw-cold-storage-ppe-and-rotation; tw-conveyor-jam-clearing-and-loto; tw-dock-leveler-and-trailer-restraint-check; tw-high-bay-order-picker-fall-protection | J97: no | K97: WebXR/shared/props.js PROPS_BUDGET
A98: coldRoomDoor | B98: prop | C98: coldRoomDoor | D98: 5 | E98: 1.98 x 2.68 x 0.28 | F98: door | G98: insulated cold-storage doorway with a PVC strip curtain | H98: 1 | I98: tw-cold-storage-ppe-and-rotation | J98: no | K98: WebXR/shared/props.js PROPS_BUDGET
A99: marinaBerth | B99: prop | C99: marinaBerth | D99: 11 | E99: 2.21 x 2.2 x 12 | F99: cleats; pedestal; breaker; pedestalLamp; extinguisherBox; spillKit; fuelPump; fuelHose; boom | G99: marina finger dock on piles with cleats, a shore-power pedestal and breaker, an extinguisher box, a spill-kit cabinet and a fuel-dock pump with boom | H99: 4 | I99: yc-fuel-dock-transfer-and-spill-kit; yc-line-handling-and-docking-in-crosswind; yc-pre-departure-safety-briefing-and-guest-count; yc-shore-power-connection-and-in-water-electrical-safety | J99: no | K99: WebXR/shared/props.js PROPS_BUDGET
A100: pickToLightShelf | B100: prop | C100: pickToLightShelf | D100: 6 | E100: 1.6 x 2.44 x 0.51 | F100: lights | G100: pick-to-light shelf module, three LED pick strips | H100: 1 | I100: tw-pick-to-light-ergonomics-and-rotation | J100: no | K100: WebXR/shared/props.js PROPS_BUDGET
A101: settlementTileRack | B101: prop | C101: settlementTileRack | D101: 6 | E101: 0.9 x 0.82 x 0.3 | F101: tiles | G101: PVC settlement-tile rack, six tiles hung face-down in two rows | H101: 1 | I101: me-oyster-reef-monitoring-and-settlement-tiles | J101: no | K101: WebXR/shared/props.js PROPS_BUDGET
A102: quadratFrame | B102: prop | C102: quadratFrame | D102: 4 | E102: 0.53 x 0.1 x 0.53 | G102: half-metre PVC quadrat with cross-strings and pin feet | H102: 1 | I102: me-kelp-transect-survey-and-photo-quadrats | J102: no | K102: WebXR/shared/props.js PROPS_BUDGET
A103: divingStage | B103: prop | C103: divingStage | D103: 5 | E103: 1.5 x 2.58 x 1.5 | F103: bail; gate | G103: diver's launch and recovery stage, grated floor, lifting bail, hinged gate | H103: 2 | I103: cd-hydraulic-tools-and-suction-hazards-underwater; cd-underwater-wet-welding-and-cutting | J103: no | K103: WebXR/shared/props.js PROPS_BUDGET
A104: drill | B104: tool | C104: drill | D104: 4 | E104: 0.08 x 0.27 x 0.32 | F104: trigger | G104: cordless drill-driver | H104: 1 | I104: bt-masonry-wall-layout-and-mortar | J104: yes | K104: WebXR/shared/toolkit.js TOOLKIT_BUDGET
A105: angleGrinder | B105: tool | C105: angleGrinder | D105: 4 | E105: 0.2 x 0.07 x 0.42 | F105: guard; disc | G105: 125 mm angle grinder with guard | H105: 1 | I105: bt-rebar-tying-and-impalement-protection | J105: yes | K105: WebXR/shared/toolkit.js TOOLKIT_BUDGET
A106: impactWrench | B106: tool | C106: impactWrench | D106: 4 | E106: 0.09 x 0.27 x 0.23 | F106: trigger | G106: 1/2 in cordless impact wrench | H106: 1 | I106: bs-structural-bolting-and-torque | J106: yes | K106: WebXR/shared/toolkit.js TOOLKIT_BUDGET
A107: torqueWrench | B107: tool | C107: torqueWrench | D107: 3 | E107: 0.04 x 0.04 x 0.51 | F107: scale | G107: click-type torque wrench | H107: 1 | I107: bs-structural-bolting-and-torque | J107: yes | K107: WebXR/shared/toolkit.js TOOLKIT_BUDGET
A108: multimeter | B108: tool | C108: multimeter | D108: 4 | E108: 0.33 x 0.2 x 0.13 | F108: screen; leadRed; leadBlack | G108: digital multimeter, live screen | H108: 0 | J108: yes | K108: WebXR/shared/toolkit.js TOOLKIT_BUDGET
A109: fourGasMeter | B109: tool | C109: fourGasMeter | D109: 3 | E109: 0.07 x 0.12 x 0.05 | F109: screen | G109: O2 / LEL / CO / H2S monitor, live screen | H109: 4 | I109: br-boom-towing-between-two-vessels; br-shoreline-cleanup-sharps-and-hazardous-debris; cs-permit-entry-and-attendant-duties; cs-ventilation-and-air-monitoring-plan | J109: yes | K109: WebXR/shared/toolkit.js TOOLKIT_BUDGET
A110: radio | B110: tool | C110: radio | D110: 4 | E110: 0.06 x 0.26 x 0.04 | F110: screen; ptt | G110: portable two-way radio | H110: 30 | I110: br-barge-loading-of-contaminated-sediment; br-beach-seine-fish-survey-and-handling; br-benthic-grab-and-invertebrate-sorting; br-bird-nesting-buffer-and-work-window; br-boom-towing-between-two-vessels; br-cold-water-immersion-and-mob-recovery; br-dive-site-hazard-assessment-and-jsa; br-drone-shoreline-survey; br-marine-mammal-observer-during-pile-driving; br-restoration-data-qa-and-public-reporting; br-vhf-and-navigation-in-a-work-zone; br-volunteer-cleanup-day-safety-lead; bs-bearing-replacement-and-jacking; bs-structural-bolting-and-torque; bs-tandem-lift-girder-set; bt-formwork-stripping-and-reshoring; bt-masonry-wall-layout-and-mortar; bt-rebar-tying-and-impalement-protection; cs-non-entry-retrieval-and-tripod; cs-permit-entry-and-attendant-duties; cs-ventilation-and-air-monitoring-plan; hw-banquet-room-flip-and-staging; hw-flatwork-ironer-and-folder-guarding; hw-housekeeping-cart-and-chemical-safety; me-eelgrass-seed-collection-and-nursery; me-invasive-species-identification-and-reporting; me-oyster-reef-monitoring-and-settlement-tiles; me-shoreline-debris-and-microplastics-survey; me-tidal-marsh-channel-restoration-day; me-water-column-sampling-from-a-small-boat | J110: yes | K110: WebXR/shared/toolkit.js TOOLKIT_BUDGET
A111: flashlight | B111: tool | C111: flashlight | D111: 3 | E111: 0.04 x 0.04 x 0.22 | F111: lens | G111: aluminium flashlight | H111: 4 | I111: cs-permit-entry-and-attendant-duties; ed-boiler-room-filter-change-lockout; hw-flatwork-ironer-and-folder-guarding; hw-housekeeping-cart-and-chemical-safety | J111: yes | K111: WebXR/shared/toolkit.js TOOLKIT_BUDGET
A112: tapeMeasure | B112: tool | C112: tapeMeasure | D112: 4 | E112: 0.3 x 0.07 x 0.05 | F112: blade | G112: 8 m tape, blade run out | H112: 7 | I112: bt-masonry-wall-layout-and-mortar; bt-rebar-tying-and-impalement-protection; gl-aluminium-panel-fabrication-and-brake; gl-curtain-wall-unit-setting-from-the-floor; gl-shop-drawing-takeoff-and-field-measure; gl-storefront-frame-and-glass-set-with-cups; hw-banquet-room-flip-and-staging | J112: yes | K112: WebXR/shared/toolkit.js TOOLKIT_BUDGET
A113: level | B113: tool | C113: level | D113: 3 | E113: 0.63 x 0.06 x 0.03 | F113: vials | G113: 600 mm spirit level | H113: 6 | I113: bt-masonry-wall-layout-and-mortar; gl-aluminium-panel-fabrication-and-brake; gl-curtain-wall-unit-setting-from-the-floor; gl-shop-drawing-takeoff-and-field-measure; gl-skylight-glass-replacement-and-fall-protection; op-grader-fine-grade-and-crown | J113: yes | K113: WebXR/shared/toolkit.js TOOLKIT_BUDGET
A114: hammer | B114: tool | C114: hammer | D114: 3 | E114: 0.17 x 0.03 x 0.32 | F114: head | G114: framing hammer | H114: 2 | I114: bs-bearing-replacement-and-jacking; bs-structural-bolting-and-torque | J114: yes | K114: WebXR/shared/toolkit.js TOOLKIT_BUDGET
A115: wrenchSet | B115: tool | C115: wrenchSet | D115: 2 | E115: 0.42 x 0.01 x 0.3 | F115: wrenches | G115: combination wrenches in a roll | H115: 1 | I115: ed-playground-equipment-inspection | J115: yes | K115: WebXR/shared/toolkit.js TOOLKIT_BUDGET
A116: hardHatLamp | B116: tool | C116: hardHatLamp | D116: 3 | E116: 0.29 x 0.16 x 0.29 | F116: lamp | G116: hard hat with cap lamp | H116: 1 | I116: cs-non-entry-retrieval-and-tripod | J116: yes | K116: WebXR/shared/toolkit.js TOOLKIT_BUDGET
A117: chock | B117: tool | C117: chock | D117: 2 | E117: 0.2 x 0.26 x 0.28 | F117: handle | G117: wheel chock | H117: 3 | I117: op-equipment-daily-walkaround-and-fluids; op-loader-truck-loading-and-blind-spots; tw-dock-leveler-and-trailer-restraint-check | J117: yes | K117: WebXR/shared/toolkit.js TOOLKIT_BUDGET
A118: tagLine | B118: tool | C118: tagLine | D118: 2 | E118: 0.45 x 0.08 x 0.34 | F118: hook | G118: coiled tag line with snap hook | H118: 2 | I118: bs-tandem-lift-girder-set; cs-non-entry-retrieval-and-tripod | J118: yes | K118: WebXR/shared/toolkit.js TOOLKIT_BUDGET
A119: tieDownStrap | B119: tool | C119: tieDownStrap | D119: 3 | E119: 0.43 x 0.05 x 0.14 | F119: ratchet; hook | G119: 2 in ratchet tie-down | H119: 1 | I119: hw-banquet-room-flip-and-staging | J119: yes | K119: WebXR/shared/toolkit.js TOOLKIT_BUDGET
A120: gladHandGauge | B120: tool | C120: gladHandGauge | D120: 3 | E120: 0.13 x 0.14 x 0.06 | F120: dial | G120: glad-hand air gauge, live dial | H120: 1 | I120: po-yard-hostler-and-pedestrian-separation | J120: yes | K120: WebXR/shared/toolkit.js TOOLKIT_BUDGET
A121: tireGauge | B121: tool | C121: tireGauge | D121: 3 | E121: 0.03 x 0.02 x 0.31 | F121: bar | G121: dual-foot truck tyre gauge | H121: 0 | J121: yes | K121: WebXR/shared/toolkit.js TOOLKIT_BUDGET
A122: creeper | B122: tool | C122: creeper | D122: 3 | E122: 0.44 x 0.13 x 0.98 | F122: casters | G122: mechanic's creeper | H122: 0 | J122: yes | K122: WebXR/shared/toolkit.js TOOLKIT_BUDGET
A123: hoseReel | B123: tool | C123: hoseReel | D123: 4 | E123: 0.28 x 0.37 x 0.39 | F123: drum; nozzle | G123: air hose reel | H123: 2 | I123: bt-masonry-wall-layout-and-mortar; hz-decon-corridor-for-a-mass-casualty-drill | J123: yes | K123: WebXR/shared/toolkit.js TOOLKIT_BUDGET
A124: glassVacuumLifter | B124: tool | C124: glassVacuumLifter | D124: 4 | E124: 0.55 x 0.24 x 0.06 | F124: gauge | G124: two-cup manual glass vacuum lifter, live vacuum gauge | H124: 5 | I124: gl-glass-handling-cart-and-crane-vacuum-lifter; gl-skylight-glass-replacement-and-fall-protection; gl-storefront-frame-and-glass-set-with-cups; gl-swing-stage-glazing-and-sealant; gl-tempered-glass-breakage-and-cleanup | J124: yes | K124: WebXR/shared/toolkit.js TOOLKIT_BUDGET
A125: gulls | B125: wildlife | C125: gulls | D125: 24 | G125: 8 per group, circle | H125: 0 | J125: no | K125: WebXR/shared/wildlife.js WILDLIFE_BUDGET
A126: pelicans | B126: wildlife | C126: pelicans | D126: 12 | G126: 4 per group, glide | H126: 0 | J126: no | K126: WebXR/shared/wildlife.js WILDLIFE_BUDGET
A127: shorebirds | B127: wildlife | C127: shorebirds | D127: 12 | G127: 6 per group, dash | H127: 0 | J127: no | K127: WebXR/shared/wildlife.js WILDLIFE_BUDGET
A128: seals | B128: wildlife | C128: seals | D128: 7 | G128: 3 per group, bask | H128: 0 | J128: no | K128: WebXR/shared/wildlife.js WILDLIFE_BUDGET
A129: fish | B129: wildlife | C129: fish | D129: 1 | G129: 60 per group, school | H129: 0 | J129: no | K129: WebXR/shared/wildlife.js WILDLIFE_BUDGET
A130: ray | B130: wildlife | C130: ray | D130: 2 | G130: 1 per group, figure-eight | H130: 0 | J130: no | K130: WebXR/shared/wildlife.js WILDLIFE_BUDGET
A131: crab | B131: wildlife | C131: crab | D131: 4 | G131: 1 per group, sidestep | H131: 0 | J131: no | K131: WebXR/shared/wildlife.js WILDLIFE_BUDGET
A132: skyDome | B132: sky | C132: sky dome | D132: 16 | G132: 900 vertices, 10 clouds, 240 stars | H132: 0 | J132: no | K132: WebXR/shared/sky.js SKY_BUDGET

Sheet Vehicles and Boats
A1: name | B1: family | C1: build | D1: meshes | E1: footprint | F1: description | G1: stationCount | H1: unity | I1: source
A2: semiTractor | B2: vehicle | C2: semiTractor | D2: 24 | E2: 3.02 x 3.95 x 6.86 | F2: Class 8 conventional tractor, tandem drive. | G2: 2 | H2: yes | I2: WebXR/shared/fleet.js semiTractor() doc comment; FLEET_BUDGET
A3: semiTractor:sleeper | B3: vehicle | C3: semiTractor | D3: 24 | E3: 3.02 x 4 x 8.66 | F3: Class 8 conventional tractor, tandem drive. | G3: 2 | H3: yes | I3: WebXR/shared/fleet.js semiTractor() doc comment; FLEET_BUDGET
A4: trailer:dryVan | B4: vehicle | C4: trailer | D4: 14 | E4: 2.63 x 4.11 x 16.27 | F4: Semi-trailer. | G4: 3 | H4: yes | I4: WebXR/shared/fleet.js trailer() doc comment; FLEET_BUDGET
A5: trailer:flatbed | B5: vehicle | C5: trailer | D5: 13 | E5: 2.66 x 1.53 x 14.69 | F5: Semi-trailer. | G5: 3 | H5: yes | I5: WebXR/shared/fleet.js trailer() doc comment; FLEET_BUDGET
A6: trailer:reefer | B6: vehicle | C6: trailer | D6: 17 | E6: 2.63 x 4.11 x 16.7 | F6: Semi-trailer. | G6: 3 | H6: yes | I6: WebXR/shared/fleet.js trailer() doc comment; FLEET_BUDGET
A7: trailer:tanker | B7: vehicle | C7: trailer | D7: 14 | E7: 2.63 x 3.26 x 12.94 | F7: Semi-trailer. | G7: 3 | H7: yes | I7: WebXR/shared/fleet.js trailer() doc comment; FLEET_BUDGET
A8: trailer:pup | B8: vehicle | C8: trailer | D8: 13 | E8: 2.63 x 4.11 x 8.65 | F8: Semi-trailer. | G8: 3 | H8: yes | I8: WebXR/shared/fleet.js trailer() doc comment; FLEET_BUDGET
A9: tractorTrailer | B9: vehicle | C9: tractorTrailer | D9: 38 | E9: 3.02 x 4.11 x 20.71 | F9: A coupled tractor-trailer: `opts.cab` and `opts.trailer` pick the pieces, the trailer's kingpin sits over the fifth wheel. | G9: 7 | H9: yes | I9: WebXR/shared/fleet.js tractorTrailer() doc comment; FLEET_BUDGET
A10: boxTruck | B10: vehicle | C10: boxTruck | D10: 21 | E10: 3.02 x 4.05 x 10 | F10: Class 6 box truck: conventional cab and a 26 ft dry box with a roll-up rear door. | G10: 3 | H10: yes | I10: WebXR/shared/fleet.js boxTruck() doc comment; FLEET_BUDGET
A11: pickup | B11: vehicle | C11: pickup | D11: 17 | E11: 2.39 x 1.93 x 5.92 | F11: Full-size crew-cab pickup, 5.9 m × 2.03 m × 1.95 m, 1.65 m bed. | G11: 11 | H11: yes | I11: WebXR/shared/fleet.js pickup() doc comment; FLEET_BUDGET
A12: sedan | B12: vehicle | C12: sedan | D12: 17 | E12: 2.23 x 1.45 x 4.92 | F12: Mid-size sedan, 4.9 m × 1.85 m × 1.45 m. | G12: 10 | H12: yes | I12: WebXR/shared/fleet.js sedan() doc comment; FLEET_BUDGET
A13: cargoVan | B13: vehicle | C13: cargoVan | D13: 18 | E13: 2.41 x 2.72 x 5.99 | F13: High-roof full-size cargo van, 5.93 m × 2.05 m × 2.75 m. | G13: 5 | H13: yes | I13: WebXR/shared/fleet.js cargoVan() doc comment; FLEET_BUDGET
... A33: rov | B33: boat | C33: rov | D33: 9 | E33: 0.62 x 0.55 x 1.01 | F33: Observation-class ROV: 0.9 m long, 0.62 m wide, 0.5 m tall, an open aluminium frame under a yellow syntactic-foam flotation block, a camera dome forward, two LED lamps beside it, four thrusters (two horizontal aft, two vertical), a single-function manipulator jaw forward-low and a tether termination on top. | G33: 1 | H33: yes | I33: WebXR/shared/fleet.js rov() doc comment; FLEET_BUDGET

Sheet Worlds
A1: name | B1: page | C1: bounds | D1: zones | E1: sites | F1: landmarks | G1: routes | H1: meshBudget | I1: quests | J1: eggs | K1: activities | L1: source
A2: Bay World | B2: WebXR/dist/bayworld.html | C2: x -1200..1200, z -800..800 | D2: 16 | E2: 50 | F2: 28 | G2: 15 roads | H2: 100-3600 | I2: 113 | J2: 34 | K2: 6 | L2: WebXR/shared/bayworld-data.js; WebXR/bayworld/js/quests-data.js
A3: The Deep | B3: WebXR/dist/underwater.html | C3: x -1000..1000, z -700..700 | D3: 14 | E3: 32 | F3: 25 | G3: 17 lines | H3: 100-1400 | I3: 40 | J3: 24 | K3: 4 | L3: WebXR/shared/underwater-data.js; WebXR/underwater/js/dives-data.js
A4: Fairway Park | B4: WebXR/dist/fairway.html | C4: x -300..300, z -50..350 | D4: 8 | E4: 9 holes | G4: par 36 over 9 holes | H4: 130-900 | L4: WebXR/shared/fairway-data.js
A5: Bay Regatta | B5: WebXR/dist/regatta.html | C5: x -1200..1200, z -800..800 | D5: 4 | E5: 12 yachts | G5: 3 courses | K5: 5 | L5: WebXR/shared/yacht-fleet.js; WebXR/regatta/js/courses.js; WebXR/regatta/js/events.js; bounds from WebXR/shared/bayworld-data.js
A6: golden-gate-deck (scenic district) | B6: WebXR/dist/smartcity-x.html | H6: 120 | L6: WebXR/smartcity/js/districts.js DISTRICTS (plaza: false), SCENIC_BUDGET
A7: bay-underwater (scenic district) | B7: WebXR/dist/smartcity-x.html | H7: 120 | L7: WebXR/smartcity/js/districts.js DISTRICTS (plaza: false), SCENIC_BUDGET
A8: gym-court (scenic district) | B8: WebXR/dist/smartcity-x.html | H8: 120 | L8: WebXR/smartcity/js/districts.js DISTRICTS (plaza: false), SCENIC_BUDGET
A9: open-range (scenic district) | B9: WebXR/dist/smartcity-x.html | H9: 120 | L9: WebXR/smartcity/js/districts.js DISTRICTS (plaza: false), SCENIC_BUDGET
A10: fairway-park (scenic district) | B10: WebXR/dist/smartcity-x.html | H10: 120 | L10: WebXR/smartcity/js/districts.js DISTRICTS (plaza: false), SCENIC_BUDGET
A11: bay-world (scenic district) | B11: WebXR/dist/smartcity-x.html | H11: 120 | L11: WebXR/smartcity/js/districts.js DISTRICTS (plaza: false), SCENIC_BUDGET
A12: the-deep (scenic district) | B12: WebXR/dist/smartcity-x.html | H12: 120 | L12: WebXR/smartcity/js/districts.js DISTRICTS (plaza: false), SCENIC_BUDGET

Sheet UI Surfaces
A1: name | B1: path | C1: purpose | D1: inputModes | E1: hudPanelCount | F1: hudPanels | G1: source
A2: Break Room Arcade | B2: WebXR/dist/arcade.html | C2: The training platform's other Easter egg: a row of four retro cabinets in the crew break room, each an original 2D canvas game — a climbing platformer, a side-scrolling runner, a falling-block stacker and a lane-crossing dodger — with pixel art, a chiptune soundtrack and local high scores. | D2: flat; keyboard; touch; gamepad | E2: 1 | F2: hud-top | G2: WebXR/dist/arcade.html (<title>, meta description, input listeners, element ids)
A3: Bay Atlas | B3: WebXR/dist/atlas.html | C3: Every Bay World training site and landmark with its programmes and deep links, over a map: drawn from the world's own data, or over a real-world Mapbox map when you supply your own token. | D3: flat; keyboard; touch | E3: 0 | G3: WebXR/dist/atlas.html (<title>, meta description, input listeners, element ids)
A4: Bay World | B4: WebXR/dist/bayworld.html | C4: A free-roam open-world city on the training platform: walk or drive anywhere, day and night, traffic and weather, a map, and missions that launch the platform's real training stations. | D4: flat; keyboard; touch; gamepad | E4: 14 | F4: hud; hud-buttons; hud-clock; hud-credits; hud-map-btn; hud-minimap; hud-objective; hud-phone; hud-prompt; hud-radio-btn; hud-reputation; hud-stats; hud-weather; hud-zone | G4: WebXR/dist/bayworld.html (<title>, meta description, input listeners, element ids)
A5: Fairway Park | B5: WebXR/dist/fairway.html | C5: An original nine-hole golf course and an outdoor sports facility on the training platform: stroke play with a timed swing meter, real scoring, and a groundskeeper's log that scores course care alongside it. | D5: flat; keyboard; touch; gamepad | E5: 8 | F5: hud; hud-care; hud-clubs; hud-hole; hud-lie; hud-meter; hud-score; hud-wind | G5: WebXR/dist/fairway.html (<title>, meta description, input listeners, element ids)
A6: Holodeck ~ Speak a Simulation Into Existence | B6: WebXR/dist/holodeck.html | C6: Toolbox Talk Bingo | D6: flat; vr; keyboard; touch; gamepad; hands | E6: 0 | G6: WebXR/dist/holodeck.html (<title>, meta description, input listeners, element ids)
A7: Training Simulators — every station | B7: WebXR/dist/index.html | C7: Every station in the training network on one page: 633 AR/VR simulators across 20 categories, with a deep link to each one. | D7: flat; keyboard | E7: 0 | G7: WebXR/dist/index.html (<title>, meta description, input listeners, element ids)
A8: Instructor Console | B8: WebXR/dist/instructor-console.html | C8: A live view of the training sessions running on this machine — or through a relay — with the content and interaction controls for each learner: where they are, what they have hit, the station's own interruptions, its weather and device profile, and the programme they are on. | D8: flat; keyboard; touch | E8: 5 | F8: panel; panel-ints; panel-steps; panel-where; panel-who | G8: WebXR/dist/instructor-console.html (<title>, meta description, input listeners, element ids)
A9: Night Highway Circuit | B9: WebXR/dist/race.html | C9: The training platform's Easter egg: an arcade racer on ten original courses (plus a Mirror class and a Battle Arena), driven in the platform's own fleet. | D9: flat; keyboard; touch; gamepad | E9: 1 | F9: huds | G9: WebXR/dist/race.html (<title>, meta description, input listeners, element ids)
A10: Bay Regatta | B10: WebXR/dist/regatta.html | C10: A fleet of twelve motor yachts on Bay World's water: hosted events with a safety briefing before every cast-off, three original race courses against the fleet, scored on marks, the no-wake zone, right of way and a clean docking. | D10: flat; keyboard; touch; gamepad | E10: 10 | F10: hud; hud-checks; hud-course; hud-course-map; hud-helm; hud-next; hud-speed; hud-time; hud-warn; hud-yacht | G10: WebXR/dist/regatta.html (<title>, meta description, input listeners, element ids)
A11: SmartCiti.X ~VR Simulators | B11: WebXR/dist/smartcity-x.html | C11: Training Activity Record | D11: flat; vr; ar; keyboard; touch; gamepad; hands | E11: 0 | G11: WebXR/dist/smartcity-x.html (<title>, meta description, input listeners, element ids)
A12: Trade Skills Simulator | B12: WebXR/dist/trade-skills-simulator.html | C12: Trade Skills Simulator | D12: flat; vr; keyboard; touch; gamepad; hands | E12: 17 | F12: hud-combo; hud-count; hud-cue; hud-feedback; hud-fill; hud-gesture; hud-hint; hud-metrics; hud-mission; hud-objective; hud-progress; hud-rail; hud-room; hud-score; hud-step; hud-timer; hud-track | G12: WebXR/dist/trade-skills-simulator.html (<title>, meta description, input listeners, element ids)
A13: The Deep | B13: WebXR/dist/underwater.html | C13: A dive game under the bay on the training platform: swim or pilot an ROV over a large seabed, a buddy line, an ascent line at every site, a reserve you watch rather than count, and job boards that launch the platform's real dive and restoration stations. | D13: flat; keyboard; touch; gamepad | E13: 20 | F13: hud; hud-activities-btn; hud-activity; hud-buttons; hud-clock; hud-craft; hud-credits; hud-light; hud-map-btn; hud-minimap; hud-objective; hud-prompt; hud-reputation; hud-reserve; hud-reserve-fill; hud-reserve-word; hud-slate; hud-stats; hud-surface-btn; hud-zone | G13: WebXR/dist/underwater.html (<title>, meta description, input listeners, element ids)
A14: Air Quality — Monitoring and Control — training track | B14: WebXR/dist/tracks/air-quality-monitoring.html | C14: Air Quality — Monitoring and Control: a twenty-level training track, 1540 lessons across 6 stations. | D14: flat | E14: 0 | G14: WebXR/dist/tracks/air-quality-monitoring.html (<title>, meta description, input listeners, element ids)
A15: Airline Cabin and Flight Crew — AFA-CWA and ALPA — training track | B15: WebXR/dist/tracks/airline-cabin-and-flight-crew.html | C15: Airline Cabin and Flight Crew — AFA-CWA and ALPA: a twenty-level training track, 1552 lessons across 8 stations. | D15: flat | E15: 0 | G15: WebXR/dist/tracks/airline-cabin-and-flight-crew.html (<title>, meta description, input listeners, element ids)
A16: Aviation Maintenance and Ground — IAM/TWU Ramp and Line — training track | B16: WebXR/dist/tracks/aviation-maintenance-and-ground.html | C16: Aviation Maintenance and Ground — IAM/TWU Ramp and Line: a twenty-level training track, 1649 lessons across 8 stations. | D16: flat | E16: 0 | G16: WebXR/dist/tracks/aviation-maintenance-and-ground.html (<title>, meta description, input listeners, element ids)
A17: Bartending — Behind the Bar — training track | B17: WebXR/dist/tracks/bartending-course.html | C17: Bartending — Behind the Bar: a twenty-level training track, 1661 lessons across 16 stations. | D17: flat | E17: 0 | G17: WebXR/dist/tracks/bartending-course.html (<title>, meta description, input listeners, element ids)
A18: Basketball Fundamentals — training track | B18: WebXR/dist/tracks/basketball-fundamentals.html | C18: Basketball Fundamentals: a twenty-level training track, 1680 lessons across 18 stations. | D18: flat | E18: 0 | G18: WebXR/dist/tracks/basketball-fundamentals.html (<title>, meta description, input listeners, element ids)
A19: Bay Area Union Edition — Sheet Metal, Bridge, Port and Marine — training track | B19: WebXR/dist/tracks/bay-area-union-edition.html | C19: Bay Area Union Edition — Sheet Metal, Bridge, Port and Marine: a twenty-level training track, 1612 lessons across 42 stations. | D19: flat | E19: 0 | G19: WebXR/dist/tracks/bay-area-union-edition.html (<title>, meta description, input listeners, element ids)
A20: SF Bay Restoration & Cleanup — Maritime and Underwater — training track | B20: WebXR/dist/tracks/bay-restoration-maritime-underwater.html | C20: SF Bay Restoration &amp; Cleanup — Maritime and Underwater: a twenty-level training track, 1641 lessons across 35 stations. | D20: flat | E20: 0 | G20: WebXR/dist/tracks/bay-restoration-maritime-underwater.html (<title>, meta description, input listeners, element ids)
A21: Bridge and Structural Trades — training track | B21: WebXR/dist/tracks/bridge-and-structural.html | C21: Bridge and Structural Trades: a twenty-level training track, 1620 lessons across 7 stations. | D21: flat | E21: 0 | G21: WebXR/dist/tracks/bridge-and-structural.html (<title>, meta description, input listeners, element ids)
A22: Builders — Carpenters, Laborers and Masons — training track | B22: WebXR/dist/tracks/builders-trades.html | C22: Builders — Carpenters, Laborers and Masons: a twenty-level training track, 1633 lessons across 8 stations. | D22: flat | E22: 0 | G22: WebXR/dist/tracks/builders-trades.html (<title>, meta description, input listeners, element ids)
A23: Cement Masons and Plasterers — training track | B23: WebXR/dist/tracks/cement-masons-and-plasterers.html | C23: Cement Masons and Plasterers: a twenty-level training track, 1590 lessons across 8 stations. | D23: flat | E23: 0 | G23: WebXR/dist/tracks/cement-masons-and-plasterers.html (<title>, meta description, input listeners, element ids)
A24: Civic Leadership and Emotional Intelligence — training track | B24: WebXR/dist/tracks/civic-leadership-and-ei.html | C24: Civic Leadership and Emotional Intelligence: a twenty-level training track, 1600 lessons across 17 stations. | D24: flat | E24: 0 | G24: WebXR/dist/tracks/civic-leadership-and-ei.html (<title>, meta description, input listeners, element ids)
A25: Commercial Diving & Scientific Scuba — training track | B25: WebXR/dist/tracks/commercial-diving-and-scientific-scuba.html | C25: Commercial Diving &amp; Scientific Scuba: a twenty-level training track, 1650 lessons across 8 stations. | D25: flat | E25: 0 | G25: WebXR/dist/tracks/commercial-diving-and-scientific-scuba.html (<title>, meta description, input listeners, element ids)
... A67: Yacht & Charter Crew — training track | B67: WebXR/dist/tracks/yacht-and-charter-crew.html | C67: Yacht &amp; Charter Crew: a twenty-level training track, 1552 lessons across 8 stations. | D67: flat | E67: 0 | G67: WebXR/dist/tracks/yacht-and-charter-crew.html (<title>, meta description, input listeners, element ids)

Sheet Unions
A1: id | B1: abbrev | C1: name | D1: trainingBody | E1: programmes
A2: aaup | B2: AAUP | C2: American Association of University Professors | D2: aaup-training
A3: aea | B3: Actors' Equity | C3: Actors' Equity Association | D3: aea-training | E3: screen-and-media-crafts
A4: afa-cwa | B4: AFA-CWA | C4: Association of Flight Attendants-CWA | D4: afa-cwa-training | E4: airline-cabin-and-flight-crew
A5: afge | B5: AFGE | C5: American Federation of Government Employees | D5: afge-training
A6: afl-cio-maritime-trades | B6: MTD (Maritime) | C6: Maritime Trades Department, AFL-CIO | D6: afl-cio-maritime-trades-training
A7: afl-cio-metal-trades | B7: AFL-CIO MTD | C7: Metal Trades Department, AFL-CIO | D7: afl-cio-metal-trades-training
A8: afm | B8: AFM | C8: American Federation of Musicians | D8: afm-training | E8: screen-and-media-crafts
A9: afm-local6 | B9: AFM Local 6 | C9: American Federation of Musicians Local 6 | D9: afm-local6-training
A10: afsa | B10: AFSA | C10: American Federation of School Administrators | D10: afsa-training
A11: afscme | B11: AFSCME | C11: American Federation of State, County and Municipal Employees | D11: afscme-training | E11: air-quality-monitoring; basketball-fundamentals; bay-restoration-maritime-underwater; civic-leadership-and-ei; culinary-kitchen; dental-careers-unspoken-smiles; dental-hygiene-unspoken-smiles; first-responders; grounds-and-landscaping; job-readiness-edition; marine-ecology-and-restoration; outbreak-response-who; wojrc-pathway-edition
A12: afscme-local3299 | B12: AFSCME Local 3299 | C12: AFSCME Local 3299 | D12: afscme-local3299-training
A13: aft | B13: AFT | C13: American Federation of Teachers | D13: aft-training | E13: education-support-staff
A14: alpa | B14: ALPA | C14: Air Line Pilots Association, International | D14: alpa-training | E14: airline-cabin-and-flight-crew
A15: amo | B15: AMO | C15: American Maritime Officers | D15: amo-training
A16: apwu | B16: APWU | C16: American Postal Workers Union | D16: apwu-training | E16: postal-and-mail-processing
A17: atu | B17: ATU | C17: Amalgamated Transit Union | D17: atu-training | E17: transit-ramp
A18: atu-local192 | B18: ATU Local 192 | C18: Amalgamated Transit Union Local 192 | D18: atu-local192-training
A19: atu-local265 | B19: ATU Local 265 | C19: Amalgamated Transit Union Local 265 | D19: atu-local265-training
A20: bac | B20: BAC | C20: International Union of Bricklayers and Allied Craftworkers | D20: bac-imi | E20: builders-trades
A21: bac-local3-ca | B21: BAC Local 3 CA | C21: Bricklayers and Allied Craftworkers Local 3 California | D21: bac-local3-ca-training
A22: bctgm | B22: BCTGM | C22: Bakery, Confectionery, Tobacco Workers and Grain Millers International Union | D22: bctgm-training
A23: blet | B23: BLET | C23: Brotherhood of Locomotive Engineers and Trainmen | D23: blet-training | E23: railroad-crafts
A24: bmwed | B24: BMWED | C24: Brotherhood of Maintenance of Way Employes Division | D24: bmwed-training | E24: railroad-crafts
A25: brs | B25: BRS | C25: Brotherhood of Railroad Signalmen | D25: brs-training
A26: carpenters | B26: UBC | C26: United Brotherhood of Carpenters and Joiners of America | D26: carpenters-ictf | E26: bay-area-union-edition; bay-restoration-maritime-underwater; builders-trades; commercial-diving-and-scientific-scuba; fall-protection; hunters-point-bay-restoration
A27: carpenters-local22 | B27: Carpenters Local 22 | C27: United Brotherhood of Carpenters Local 22 | D27: carpenters-local22-training
A28: cna | B28: CNA | C28: California Nurses Association | E28: outbreak-response-who
A29: csea | B29: CSEA | C29: California School Employees Association | D29: csea-training | E29: education-support-staff
A30: cwa | B30: CWA | C30: Communications Workers of America | D30: cwa-training | E30: airline-cabin-and-flight-crew; fall-protection; marine-ecology-and-restoration; screen-and-media-crafts
A31: dpe | B31: DPE | C31: Department for Professional Employees, AFL-CIO | D31: dpe-training
A32: fast | B32: FAST | C32: Food & Allied Service Trades Department, AFL-CIO | D32: fast-training
A33: fop | B33: FOP | C33: Fraternal Order of Police | E33: first-responders
A34: iaff | B34: IAFF | C34: International Association of Fire Fighters | D34: iaff-training | E34: confined-space; first-responders; hazmat-environmental; situational-awareness
A35: iam | B35: IAM | C35: International Association of Machinists and Aerospace Workers | D35: iam-winpisinger-center | E35: aviation-maintenance-and-ground; transit-ramp
A36: iatse | B36: IATSE | C36: International Alliance of Theatrical Stage Employees | D36: iatse-training-trust | E36: live-events; rigging-lifting; screen-and-media-crafts
A37: iatse-local16 | B37: IATSE Local 16 | C37: IATSE Local 16 | D37: iatse-local16-training
A38: ibb | B38: IBB | C38: International Brotherhood of Boilermakers, Iron Ship Builders, Blacksmiths, Forgers and Helpers | D38: boilermakers-local-549 | E38: insulators-and-boilermakers
A39: ibew | B39: IBEW | C39: International Brotherhood of Electrical Workers | D39: ibew-neca-jatc | E39: electrical-first-period; energy-transition; ports-maritime-ecology; situational-awareness; transit-ramp; water-and-gas-utility-crews
A40: ibew-local1245 | B40: IBEW Local 1245 | C40: IBEW Local 1245 | D40: ibew-local1245-training
A41: ibew-local595 | B41: IBEW Local 595 | C41: IBEW Local 595 | D41: ibew-local595-training
A42: ibew-local6 | B42: IBEW Local 6 | C42: IBEW Local 6 | D42: ibew-local6-training
A43: ibu | B43: IBU | C43: Inlandboatmen's Union of the Pacific | D43: ilwu-pma-training | E43: bay-area-union-edition; bay-restoration-maritime-underwater; hunters-point-bay-restoration; ports-maritime-ecology; yacht-and-charter-crew
A44: ifpte | B44: IFPTE | C44: International Federation of Professional and Technical Engineers | D44: ifpte-training
A45: ifpte-local21 | B45: IFPTE Local 21 | C45: IFPTE Local 21 | D45: ifpte-local21-training
A46: ila | B46: ILA | C46: International Longshoremen's Association | D46: ila-training
A47: ilwu | B47: ILWU | C47: International Longshore and Warehouse Union | D47: ilwu-pma-training | E47: bay-area-union-edition; bay-restoration-maritime-underwater; job-readiness-edition; port-operations; ports-maritime-ecology; rigging-lifting
A48: insulators | B48: IAHFIAW | C48: International Association of Heat and Frost Insulators and Allied Workers | D48: insulators-local-16 | E48: insulators-and-boilermakers
A49: ironworkers | B49: IW | C49: International Association of Bridge, Structural, Ornamental and Reinforcing Iron Workers | D49: ironworkers-impact | E49: bay-area-union-edition; bridge-and-structural; fall-protection; rigging-lifting; situational-awareness
A50: ironworkers-local377 | B50: Ironworkers Local 377 | C50: Ironworkers Local 377 | D50: ironworkers-local377-training
A51: iue-cwa | B51: IUE-CWA | C51: IUE-CWA, the Industrial Division of the Communications Workers of America | D51: iue-cwa-training
A52: iuec | B52: IUEC | C52: International Union of Elevator Constructors | D52: neiep-training | E52: elevator-constructors
A53: iuec-local8 | B53: IUEC Local 8 | C53: International Union of Elevator Constructors Local 8 | D53: iuec-local8-training
A54: iuoe | B54: IUOE | C54: International Union of Operating Engineers | D54: iuoe-training | E54: air-quality-monitoring; bay-area-union-edition; bay-restoration-maritime-underwater; bridge-and-structural; builders-trades; confined-space; heavy-equipment-operators; hunters-point-bay-restoration; hunters-point-can-we-live; property-management; rigging-lifting; stationary-engineer
A55: iuoe-local3 | B55: IUOE Local 3 | C55: International Union of Operating Engineers Local 3 | D55: iuoe-local3-training | E55: bay-restoration-maritime-underwater; hunters-point-bay-restoration
A56: iupat | B56: IUPAT | C56: International Union of Painters and Allied Trades | D56: iupat-fti | E56: bay-area-union-edition; bridge-and-structural; glaziers-and-architectural-metal
A57: iupat-dc16 | B57: IUPAT DC 16 | C57: IUPAT District Council 16 | D57: iupat-dc16-glaziers | E57: glaziers-and-architectural-metal
A58: liuna | B58: LIUNA | C58: Laborers' International Union of North America | D58: liuna-training-fund | E58: air-quality-monitoring; bay-restoration-maritime-underwater; bridge-and-structural; builders-trades; commercial-diving-and-scientific-scuba; confined-space; first-responders; grounds-and-landscaping; hazmat-environmental; hunters-point-bay-restoration; hunters-point-can-we-live; marine-ecology-and-restoration; ports-maritime-ecology; situational-awareness
A59: meba | B59: MEBA | C59: Marine Engineers' Beneficial Association | D59: meba-calhoon-school | E59: bay-area-union-edition; bay-restoration-maritime-underwater; port-operations; yacht-and-charter-crew
A60: mfow | B60: MFOW | C60: Marine Firemen's Union | D60: mfow-training
A61: mmp | B61: MM&P | C61: International Organization of Masters, Mates & Pilots | D61: mmp-training
A62: nabtu | B62: NABTU | C62: North America's Building Trades Unions | D62: nabtu-training
A63: naemt | B63: NAEMT | C63: National Association of Emergency Medical Technicians | D63: naemt-courses
A64: nage | B64: NAGE | C64: National Association of Government Employees | E64: first-responders
A65: nalc | B65: NALC | C65: National Association of Letter Carriers | D65: nalc-training | E65: postal-and-mail-processing
A66: napfe | B66: NAPFE | C66: National Alliance of Postal and Federal Employees | D66: napfe-training
A67: nasw | B67: NASW | C67: National Association of Social Workers | D67: nasw-code-of-ethics | E67: first-responders
A68: natca | B68: NATCA | C68: National Air Traffic Controllers Association | D68: natca-training
A69: nea | B69: NEA | C69: National Education Association | D69: nea-training
A70: newsguild-cwa | B70: TNG-CWA | C70: The NewsGuild-CWA | D70: newsguild-cwa-training | E70: screen-and-media-crafts
A71: nffe | B71: NFFE | C71: National Federation of Federal Employees | D71: nffe-training
A72: nnu | B72: NNU | C72: National Nurses United | E72: outbreak-response-who
A73: npmhu | B73: NPMHU | C73: National Postal Mail Handlers Union | D73: npmhu-training | E73: postal-and-mail-processing
A74: nrlca | B74: NRLCA | C74: National Rural Letter Carriers' Association | D74: nrlca-training
A75: nteu | B75: NTEU | C75: National Treasury Employees Union | D75: nteu-training
A76: nuhw | B76: NUHW | C76: National Union of Healthcare Workers | D76: nuhw-training | E76: healthcare-support
A77: opcmia | B77: OPCMIA | C77: Operative Plasterers' and Cement Masons' International Association | D77: opcmia-local-300 | E77: cement-masons-and-plasterers
A78: pass-union | B78: PASS | C78: Professional Aviation Safety Specialists | D78: pass-union-training
A79: rwdsu | B79: RWDSU | C79: Retail, Wholesale and Department Store Union | D79: rwdsu-training
A80: sag-aftra | B80: SAG-AFTRA | C80: Screen Actors Guild-American Federation of Television and Radio Artists | D80: sag-aftra-training | E80: screen-and-media-crafts
A81: seiu | B81: SEIU | C81: Service Employees International Union | D81: seiu-training | E81: basketball-fundamentals; bay-restoration-maritime-underwater; civic-leadership-and-ei; culinary-kitchen; dental-careers-unspoken-smiles; dental-hygiene-unspoken-smiles; first-responders; grounds-and-landscaping; healthcare-support; job-readiness-edition; marine-ecology-and-restoration; outbreak-response-who; property-management; sewing-garment-trades; wojrc-pathway-edition
A82: seiu-1021 | B82: SEIU 1021 | C82: SEIU 1021 | D82: seiu-1021-training | E82: first-responders; marine-ecology-and-restoration
A83: seiu-uhw | B83: SEIU-UHW | C83: SEIU United Healthcare Workers West | D83: seiu-uhw-training | E83: healthcare-support
A84: seiu-uswtw | B84: SEIU-USWW | C84: SEIU United Service Workers West | D84: seiu-uswtw-training | E84: property-management
A85: siu | B85: SIU | C85: Seafarers International Union | D85: siu-paul-hall-center | E85: bay-area-union-edition; bay-restoration-maritime-underwater; port-operations; yacht-and-charter-crew
A86: smart | B86: SMART | C86: International Association of Sheet Metal, Air, Rail and Transportation Workers | D86: smart-iti | E86: bay-area-union-edition; railroad-crafts
A87: smart-local104 | B87: SMART Local 104 | C87: Sheet Metal Workers Local 104 | D87: smart-local104-training
A88: smart-td | B88: SMART-TD | C88: SMART Transportation Division | D88: smarttd-training | E88: railroad-crafts
A89: spfpa | B89: SPFPA | C89: International Union, Security, Police and Fire Professionals of America | D89: spfpa-training
A90: sup | B90: SUP | C90: Sailors' Union of the Pacific | D90: sup-training
A91: tcu | B91: TCU/IAM | C91: Transportation Communications Union/IAM | D91: tcu-training
A92: teamsters | B92: IBT | C92: International Brotherhood of Teamsters | D92: teamsters-training | E92: hunters-point-bay-restoration; hunters-point-can-we-live; job-readiness-edition; port-operations; warehouse-and-logistics-automation; wojrc-pathway-edition
A93: ttd | B93: TTD | C93: Transportation Trades Department, AFL-CIO | D93: ttd-training
A94: twu | B94: TWU | C94: Transport Workers Union of America | D94: twu-training | E94: aviation-maintenance-and-ground; transit-ramp
A95: twu-local250a | B95: TWU Local 250-A | C95: Transport Workers Union Local 250-A | D95: twu-local250a-training
A96: ua | B96: UA | C96: United Association of Journeymen and Apprentices of the Plumbing and Pipe Fitting Industry of the United States and Canada | D96: ua-apprenticeship | E96: confined-space; hunters-point-bay-restoration; plumbers-and-pipefitters; situational-awareness
A97: ua-local483 | B97: UA Local 483 | C97: UA Road Sprinkler Fitters Local 483 | D97: ua-local483-training
A98: uaw | B98: UAW | C98: International Union, United Automobile, Aerospace and Agricultural Implement Workers of America | D98: uaw-training
A99: ufcw | B99: UFCW | C99: United Food and Commercial Workers International Union | D99: ufcw-training | E99: dental-careers-unspoken-smiles; dental-hygiene-unspoken-smiles; grocery-and-meatpacking
A100: ulstd | B100: ULSTD | C100: Union Label and Service Trades Department, AFL-CIO | D100: ulstd-training
...

Sheet Platform Facts
A1: key | B1: value | C1: source
A2: procedures | B2: 633 | C2: WebXR/smartcity/catalog.json stations.length
A3: smartcityStations | B3: 624 | C3: WebXR/smartcity/catalog.json stations where app = smartcity
A4: tradeSkillsRooms | B4: 9 | C4: WebXR/smartcity/catalog.json stations where app = trades
A5: programmes | B5: 54 | C5: WebXR/smartcity/js/curricula.js CURRICULA.length
A6: categories | B6: 20 | C6: WebXR/smartcity/catalog.json categories.length
A7: unions | B7: 111 | C7: tools/unions.json unions.length
A8: trainingBodies | B8: 105 | C8: tools/standards.json standards where body = union
A9: standards | B9: 509 | C9: tools/standards.json standards.length
A10: competencies | B10: 64 | C10: WebXR/shared/competency.js COMPETENCIES.length
A11: programmeCompetencies | B11: 54 | C11: WebXR/shared/competency.js PROGRAMME_COMPETENCIES.length
A12: coreCompetencies | B12: 10 | C12: WebXR/shared/competency.js CORE_COMPETENCIES.length
A13: profileLevels | B13: 33 | C13: WebXR/smartcity/catalog.json profile.levels
... A50: uiPages | B50: 66 | C50: ls WebXR/dist/*.html WebXR/dist/tracks/*.html
